{"primaryContentSections":[{"kind":"declarations","declarations":[{"tokens":[{"kind":"keyword","text":"init"},{"kind":"text","text":"("},{"kind":"externalParam","text":"dateStampProperties"},{"kind":"text","text":": "},{"kind":"typeIdentifier","identifier":"doc:\/\/com.DocuSign.DocuSIgnAPI\/documentation\/DocuSignAPI\/DSAPIDateStampProperties","preciseIdentifier":"c:@M@DocuSignAPI@objc(cs)DSAPIDateStampProperties","text":"DSAPIDateStampProperties"},{"kind":"text","text":"? = nil, "},{"kind":"externalParam","text":"disallowUserResizeStamp"},{"kind":"text","text":": "},{"kind":"typeIdentifier","text":"Bool","preciseIdentifier":"s:Sb"},{"kind":"text","text":" = false, "},{"kind":"externalParam","text":"externalID"},{"kind":"text","text":": "},{"kind":"typeIdentifier","text":"String","preciseIdentifier":"s:SS"},{"kind":"text","text":"? = nil, "},{"kind":"externalParam","text":"imageType"},{"kind":"text","text":": "},{"kind":"typeIdentifier","text":"String","preciseIdentifier":"s:SS"},{"kind":"text","text":"? = nil, "},{"kind":"externalParam","text":"isDefault"},{"kind":"text","text":": "},{"kind":"typeIdentifier","text":"Bool","preciseIdentifier":"s:Sb"},{"kind":"text","text":" = false, "},{"kind":"externalParam","text":"nrdsId"},{"kind":"text","text":": "},{"kind":"typeIdentifier","text":"String","preciseIdentifier":"s:SS"},{"kind":"text","text":"? = nil, "},{"kind":"externalParam","text":"nrdsLastName"},{"kind":"text","text":": "},{"kind":"typeIdentifier","text":"String","preciseIdentifier":"s:SS"},{"kind":"text","text":"? = nil, "},{"kind":"externalParam","text":"phoneticName"},{"kind":"text","text":": "},{"kind":"typeIdentifier","text":"String","preciseIdentifier":"s:SS"},{"kind":"text","text":"? = nil, "},{"kind":"externalParam","text":"signatureFont"},{"kind":"text","text":": "},{"kind":"typeIdentifier","text":"String","preciseIdentifier":"s:SS"},{"kind":"text","text":"? = nil, "},{"kind":"externalParam","text":"signatureGroups"},{"kind":"text","text":": ["},{"kind":"typeIdentifier","identifier":"doc:\/\/com.DocuSign.DocuSIgnAPI\/documentation\/DocuSignAPI\/DSAPISignatureGroupDef","preciseIdentifier":"s:11DocuSignAPI22DSAPISignatureGroupDefV","text":"DSAPISignatureGroupDef"},{"kind":"text","text":"]? = nil, "},{"kind":"externalParam","text":"signatureId"},{"kind":"text","text":": "},{"kind":"typeIdentifier","text":"String","preciseIdentifier":"s:SS"},{"kind":"text","text":"? = nil, "},{"kind":"externalParam","text":"signatureInitials"},{"kind":"text","text":": "},{"kind":"typeIdentifier","text":"String","preciseIdentifier":"s:SS"},{"kind":"text","text":"? = nil, "},{"kind":"externalParam","text":"signatureName"},{"kind":"text","text":": "},{"kind":"typeIdentifier","text":"String","preciseIdentifier":"s:SS"},{"kind":"text","text":"? = nil, "},{"kind":"externalParam","text":"signatureType"},{"kind":"text","text":": "},{"kind":"typeIdentifier","text":"String","preciseIdentifier":"s:SS"},{"kind":"text","text":"? = nil, "},{"kind":"externalParam","text":"signatureUsers"},{"kind":"text","text":": ["},{"kind":"typeIdentifier","identifier":"doc:\/\/com.DocuSign.DocuSIgnAPI\/documentation\/DocuSignAPI\/DSAPISignatureUserDef","preciseIdentifier":"s:11DocuSignAPI21DSAPISignatureUserDefV","text":"DSAPISignatureUserDef"},{"kind":"text","text":"]? = nil, "},{"kind":"externalParam","text":"stampFormat"},{"kind":"text","text":": "},{"kind":"typeIdentifier","text":"String","preciseIdentifier":"s:SS"},{"kind":"text","text":"? = nil, "},{"kind":"externalParam","text":"stampSizeMM"},{"kind":"text","text":": "},{"kind":"typeIdentifier","text":"String","preciseIdentifier":"s:SS"},{"kind":"text","text":"? = nil)"}],"languages":["swift"],"platforms":["iOS"]}]}],"schemaVersion":{"major":0,"minor":3,"patch":0},"sections":[],"variants":[{"paths":["\/documentation\/docusignapi\/dsapiaccountsignaturedefinition\/init(datestampproperties:disallowuserresizestamp:externalid:imagetype:isdefault:nrdsid:nrdslastname:phoneticname:signaturefont:signaturegroups:signatureid:signatureinitials:signaturename:signaturetype:signatureusers:stampformat:stampsizemm:-7p0ua"],"traits":[{"interfaceLanguage":"swift"}]}],"identifier":{"url":"doc:\/\/com.DocuSign.DocuSIgnAPI\/documentation\/DocuSignAPI\/DSAPIAccountSignatureDefinition\/init(dateStampProperties:disallowUserResizeStamp:externalID:imageType:isDefault:nrdsId:nrdsLastName:phoneticName:signatureFont:signatureGroups:signatureId:signatureInitials:signatureName:signatureType:signatureUsers:stampFormat:stampSizeMM:)","interfaceLanguage":"swift"},"kind":"symbol","metadata":{"fragments":[{"kind":"identifier","text":"init"},{"kind":"text","text":"("},{"kind":"externalParam","text":"dateStampProperties"},{"kind":"text","text":": "},{"kind":"typeIdentifier","text":"DSAPIDateStampProperties","preciseIdentifier":"c:@M@DocuSignAPI@objc(cs)DSAPIDateStampProperties"},{"kind":"text","text":"?, "},{"kind":"externalParam","text":"disallowUserResizeStamp"},{"kind":"text","text":": "},{"kind":"typeIdentifier","text":"Bool","preciseIdentifier":"s:Sb"},{"kind":"text","text":", "},{"kind":"externalParam","text":"externalID"},{"kind":"text","text":": "},{"kind":"typeIdentifier","text":"String","preciseIdentifier":"s:SS"},{"kind":"text","text":"?, "},{"kind":"externalParam","text":"imageType"},{"kind":"text","text":": "},{"kind":"typeIdentifier","text":"String","preciseIdentifier":"s:SS"},{"kind":"text","text":"?, "},{"kind":"externalParam","text":"isDefault"},{"kind":"text","text":": "},{"kind":"typeIdentifier","text":"Bool","preciseIdentifier":"s:Sb"},{"kind":"text","text":", "},{"kind":"externalParam","text":"nrdsId"},{"kind":"text","text":": "},{"kind":"typeIdentifier","text":"String","preciseIdentifier":"s:SS"},{"kind":"text","text":"?, "},{"kind":"externalParam","text":"nrdsLastName"},{"kind":"text","text":": "},{"kind":"typeIdentifier","text":"String","preciseIdentifier":"s:SS"},{"kind":"text","text":"?, "},{"kind":"externalParam","text":"phoneticName"},{"kind":"text","text":": "},{"kind":"typeIdentifier","text":"String","preciseIdentifier":"s:SS"},{"kind":"text","text":"?, "},{"kind":"externalParam","text":"signatureFont"},{"kind":"text","text":": "},{"kind":"typeIdentifier","text":"String","preciseIdentifier":"s:SS"},{"kind":"text","text":"?, "},{"kind":"externalParam","text":"signatureGroups"},{"kind":"text","text":": ["},{"kind":"typeIdentifier","text":"DSAPISignatureGroupDef","preciseIdentifier":"s:11DocuSignAPI22DSAPISignatureGroupDefV"},{"kind":"text","text":"]?, "},{"kind":"externalParam","text":"signatureId"},{"kind":"text","text":": "},{"kind":"typeIdentifier","text":"String","preciseIdentifier":"s:SS"},{"kind":"text","text":"?, "},{"kind":"externalParam","text":"signatureInitials"},{"kind":"text","text":": "},{"kind":"typeIdentifier","text":"String","preciseIdentifier":"s:SS"},{"kind":"text","text":"?, "},{"kind":"externalParam","text":"signatureName"},{"kind":"text","text":": "},{"kind":"typeIdentifier","text":"String","preciseIdentifier":"s:SS"},{"kind":"text","text":"?, "},{"kind":"externalParam","text":"signatureType"},{"kind":"text","text":": "},{"kind":"typeIdentifier","text":"String","preciseIdentifier":"s:SS"},{"kind":"text","text":"?, "},{"kind":"externalParam","text":"signatureUsers"},{"kind":"text","text":": ["},{"kind":"typeIdentifier","text":"DSAPISignatureUserDef","preciseIdentifier":"s:11DocuSignAPI21DSAPISignatureUserDefV"},{"kind":"text","text":"]?, "},{"kind":"externalParam","text":"stampFormat"},{"kind":"text","text":": "},{"kind":"typeIdentifier","text":"String","preciseIdentifier":"s:SS"},{"kind":"text","text":"?, "},{"kind":"externalParam","text":"stampSizeMM"},{"kind":"text","text":": "},{"kind":"typeIdentifier","text":"String","preciseIdentifier":"s:SS"},{"kind":"text","text":"?)"}],"title":"init(dateStampProperties:disallowUserResizeStamp:externalID:imageType:isDefault:nrdsId:nrdsLastName:phoneticName:signatureFont:signatureGroups:signatureId:signatureInitials:signatureName:signatureType:signatureUsers:stampFormat:stampSizeMM:)","roleHeading":"Initializer","role":"symbol","symbolKind":"init","externalID":"s:11DocuSignAPI31DSAPIAccountSignatureDefinitionV19dateStampProperties018disallowUserResizeH010externalID9imageType9isDefault6nrdsId0S8LastName08phoneticV013signatureFont0X6Groups0xT00X8Initials0xV00xP00X5Users11stampFormat11stampSizeMMAcA09DSAPIDatehI0CSg_SbSSSgAXSbA4XSayAA22DSAPISignatureGroupDefVGSgA4XSayAA014DSAPISignatureK3DefVGSgA2Xtcfc","modules":[{"name":"DocuSignAPI"}]},"hierarchy":{"paths":[["doc:\/\/com.DocuSign.DocuSIgnAPI\/documentation\/DocuSignAPI","doc:\/\/com.DocuSign.DocuSIgnAPI\/documentation\/DocuSignAPI\/DSAPIAccountSignatureDefinition"]]},"references":{"doc://com.DocuSign.DocuSIgnAPI/documentation/DocuSignAPI/DSAPISignatureGroupDef":{"role":"symbol","title":"DSAPISignatureGroupDef","fragments":[{"kind":"keyword","text":"struct"},{"kind":"text","text":" "},{"kind":"identifier","text":"DSAPISignatureGroupDef"}],"abstract":[],"identifier":"doc:\/\/com.DocuSign.DocuSIgnAPI\/documentation\/DocuSignAPI\/DSAPISignatureGroupDef","kind":"symbol","type":"topic","navigatorTitle":[{"kind":"identifier","text":"DSAPISignatureGroupDef"}],"url":"\/documentation\/docusignapi\/dsapisignaturegroupdef"},"doc://com.DocuSign.DocuSIgnAPI/documentation/DocuSignAPI/DSAPIAccountSignatureDefinition":{"role":"symbol","title":"DSAPIAccountSignatureDefinition","fragments":[{"kind":"keyword","text":"struct"},{"kind":"text","text":" "},{"kind":"identifier","text":"DSAPIAccountSignatureDefinition"}],"abstract":[],"identifier":"doc:\/\/com.DocuSign.DocuSIgnAPI\/documentation\/DocuSignAPI\/DSAPIAccountSignatureDefinition","kind":"symbol","type":"topic","navigatorTitle":[{"kind":"identifier","text":"DSAPIAccountSignatureDefinition"}],"url":"\/documentation\/docusignapi\/dsapiaccountsignaturedefinition"},"doc://com.DocuSign.DocuSIgnAPI/documentation/DocuSignAPI":{"role":"collection","title":"DocuSignAPI","abstract":[],"identifier":"doc:\/\/com.DocuSign.DocuSIgnAPI\/documentation\/DocuSignAPI","kind":"symbol","type":"topic","url":"\/documentation\/docusignapi"},"doc://com.DocuSign.DocuSIgnAPI/documentation/DocuSignAPI/DSAPIAccountSignatureDefinition/init(dateStampProperties:disallowUserResizeStamp:externalID:imageType:isDefault:nrdsId:nrdsLastName:phoneticName:signatureFont:signatureGroups:signatureId:signatureInitials:signatureName:signatureType:signatureUsers:stampFormat:stampSizeMM:)":{"role":"symbol","title":"init(dateStampProperties:disallowUserResizeStamp:externalID:imageType:isDefault:nrdsId:nrdsLastName:phoneticName:signatureFont:signatureGroups:signatureId:signatureInitials:signatureName:signatureType:signatureUsers:stampFormat:stampSizeMM:)","fragments":[{"kind":"identifier","text":"init"},{"kind":"text","text":"("},{"kind":"externalParam","text":"dateStampProperties"},{"kind":"text","text":": "},{"kind":"typeIdentifier","text":"DSAPIDateStampProperties","preciseIdentifier":"c:@M@DocuSignAPI@objc(cs)DSAPIDateStampProperties"},{"kind":"text","text":"?, "},{"kind":"externalParam","text":"disallowUserResizeStamp"},{"kind":"text","text":": "},{"kind":"typeIdentifier","text":"Bool","preciseIdentifier":"s:Sb"},{"kind":"text","text":", "},{"kind":"externalParam","text":"externalID"},{"kind":"text","text":": "},{"kind":"typeIdentifier","text":"String","preciseIdentifier":"s:SS"},{"kind":"text","text":"?, "},{"kind":"externalParam","text":"imageType"},{"kind":"text","text":": "},{"kind":"typeIdentifier","text":"String","preciseIdentifier":"s:SS"},{"kind":"text","text":"?, "},{"kind":"externalParam","text":"isDefault"},{"kind":"text","text":": "},{"kind":"typeIdentifier","text":"Bool","preciseIdentifier":"s:Sb"},{"kind":"text","text":", "},{"kind":"externalParam","text":"nrdsId"},{"kind":"text","text":": "},{"kind":"typeIdentifier","text":"String","preciseIdentifier":"s:SS"},{"kind":"text","text":"?, "},{"kind":"externalParam","text":"nrdsLastName"},{"kind":"text","text":": "},{"kind":"typeIdentifier","text":"String","preciseIdentifier":"s:SS"},{"kind":"text","text":"?, "},{"kind":"externalParam","text":"phoneticName"},{"kind":"text","text":": "},{"kind":"typeIdentifier","text":"String","preciseIdentifier":"s:SS"},{"kind":"text","text":"?, "},{"kind":"externalParam","text":"signatureFont"},{"kind":"text","text":": "},{"kind":"typeIdentifier","text":"String","preciseIdentifier":"s:SS"},{"kind":"text","text":"?, "},{"kind":"externalParam","text":"signatureGroups"},{"kind":"text","text":": ["},{"kind":"typeIdentifier","text":"DSAPISignatureGroupDef","preciseIdentifier":"s:11DocuSignAPI22DSAPISignatureGroupDefV"},{"kind":"text","text":"]?, "},{"kind":"externalParam","text":"signatureId"},{"kind":"text","text":": "},{"kind":"typeIdentifier","text":"String","preciseIdentifier":"s:SS"},{"kind":"text","text":"?, "},{"kind":"externalParam","text":"signatureInitials"},{"kind":"text","text":": "},{"kind":"typeIdentifier","text":"String","preciseIdentifier":"s:SS"},{"kind":"text","text":"?, "},{"kind":"externalParam","text":"signatureName"},{"kind":"text","text":": "},{"kind":"typeIdentifier","text":"String","preciseIdentifier":"s:SS"},{"kind":"text","text":"?, "},{"kind":"externalParam","text":"signatureType"},{"kind":"text","text":": "},{"kind":"typeIdentifier","text":"String","preciseIdentifier":"s:SS"},{"kind":"text","text":"?, "},{"kind":"externalParam","text":"signatureUsers"},{"kind":"text","text":": ["},{"kind":"typeIdentifier","text":"DSAPISignatureUserDef","preciseIdentifier":"s:11DocuSignAPI21DSAPISignatureUserDefV"},{"kind":"text","text":"]?, "},{"kind":"externalParam","text":"stampFormat"},{"kind":"text","text":": "},{"kind":"typeIdentifier","text":"String","preciseIdentifier":"s:SS"},{"kind":"text","text":"?, "},{"kind":"externalParam","text":"stampSizeMM"},{"kind":"text","text":": "},{"kind":"typeIdentifier","text":"String","preciseIdentifier":"s:SS"},{"kind":"text","text":"?)"}],"abstract":[],"identifier":"doc:\/\/com.DocuSign.DocuSIgnAPI\/documentation\/DocuSignAPI\/DSAPIAccountSignatureDefinition\/init(dateStampProperties:disallowUserResizeStamp:externalID:imageType:isDefault:nrdsId:nrdsLastName:phoneticName:signatureFont:signatureGroups:signatureId:signatureInitials:signatureName:signatureType:signatureUsers:stampFormat:stampSizeMM:)","kind":"symbol","type":"topic","url":"\/documentation\/docusignapi\/dsapiaccountsignaturedefinition\/init(datestampproperties:disallowuserresizestamp:externalid:imagetype:isdefault:nrdsid:nrdslastname:phoneticname:signaturefont:signaturegroups:signatureid:signatureinitials:signaturename:signaturetype:signatureusers:stampformat:stampsizemm:-7p0ua"},"doc://com.DocuSign.DocuSIgnAPI/documentation/DocuSignAPI/DSAPIDateStampProperties":{"role":"symbol","title":"DSAPIDateStampProperties","fragments":[{"kind":"keyword","text":"class"},{"kind":"text","text":" "},{"kind":"identifier","text":"DSAPIDateStampProperties"}],"abstract":[{"type":"text","text":"Specifies the area in which a date stamp is placed. This parameter uses pixel positioning to draw a rectangle at the center of the stamp area. The stamp is superimposed on top of this central area.  This property contains the following information about the central rectangle:  - `DateAreaX`: The X axis position of the top-left corner. - `DateAreaY`: The Y axis position of the top-left corner. - `DateAreaWidth`: The width of the rectangle. - `DateAreaHeight`: The height of the rectangle."}],"identifier":"doc:\/\/com.DocuSign.DocuSIgnAPI\/documentation\/DocuSignAPI\/DSAPIDateStampProperties","kind":"symbol","type":"topic","navigatorTitle":[{"kind":"identifier","text":"DSAPIDateStampProperties"}],"url":"\/documentation\/docusignapi\/dsapidatestampproperties"},"doc://com.DocuSign.DocuSIgnAPI/documentation/DocuSignAPI/DSAPISignatureUserDef":{"role":"symbol","title":"DSAPISignatureUserDef","fragments":[{"kind":"keyword","text":"struct"},{"kind":"text","text":" "},{"kind":"identifier","text":"DSAPISignatureUserDef"}],"abstract":[],"identifier":"doc:\/\/com.DocuSign.DocuSIgnAPI\/documentation\/DocuSignAPI\/DSAPISignatureUserDef","kind":"symbol","type":"topic","navigatorTitle":[{"kind":"identifier","text":"DSAPISignatureUserDef"}],"url":"\/documentation\/docusignapi\/dsapisignatureuserdef"}},"variantOverrides":[{"patch":[{"op":"replace","path":"\/references\/doc:~1~1com.DocuSign.DocuSIgnAPI~1documentation~1DocuSignAPI~1DSAPIDateStampProperties\/title","value":"DSAPIDateStampProperties"},{"op":"replace","path":"\/references\/doc:~1~1com.DocuSign.DocuSIgnAPI~1documentation~1DocuSignAPI~1DSAPIDateStampProperties\/fragments","value":[{"kind":"identifier","text":"DSAPIDateStampProperties"}]}],"traits":[{"interfaceLanguage":"occ"}]}]}