{"schemaVersion":{"patch":0,"minor":3,"major":0},"hierarchy":{"paths":[["doc:\/\/com.DocuSign.DocuSIgnAPI\/documentation\/DocuSignAPI","doc:\/\/com.DocuSign.DocuSIgnAPI\/documentation\/DocuSignAPI\/DSAPILocalePolicy"]]},"identifier":{"url":"doc:\/\/com.DocuSign.DocuSIgnAPI\/documentation\/DocuSignAPI\/DSAPILocalePolicy\/init(addressFormat:addressFormatMetadata:allowRegion:calendarType:calendarTypeMetadata:cultureName:cultureNameMetadata:currencyCode:currencyCodeMetadata:currencyNegativeFormat:currencyNegativeFormatMetadata:currencyPositiveFormat:currencyPositiveFormatMetadata:customDateFormat:customSignDateFormat:customSignTimeFormat:customTimeFormat:dateFormat:dateFormatMetadata:effectiveAddressFormat:effectiveCalendarType:effectiveCurrencyCode:effectiveCurrencyNegativeFormat:effectiveCurrencyPositiveFormat:effectiveCustomDateFormat:effectiveCustomTimeFormat:effectiveDateFormat:effectiveInitialFormat:effectiveNameFormat:effectiveTimeFormat:effectiveTimeZone:initialFormat:initialFormatMetadata:nameFormat:nameFormatMetadata:signDateFormat:signDateFormatMetadata:signTimeFormat:signTimeFormatMetadata:timeFormat:timeFormatMetadata:timeZone:timeZoneMetadata:)","interfaceLanguage":"swift"},"kind":"symbol","sections":[],"variants":[{"traits":[{"interfaceLanguage":"swift"}],"paths":["\/documentation\/docusignapi\/dsapilocalepolicy\/init(addressformat:addressformatmetadata:allowregion:calendartype:calendartypemetadata:culturename:culturenamemetadata:currencycode:currencycodemetadata:currencynegativeformat:currencynegativeformatmetadata:currencypositiveformat:currencypo-4f49g"]}],"metadata":{"fragments":[{"text":"init","kind":"identifier"},{"text":"(","kind":"text"},{"text":"addressFormat","kind":"externalParam"},{"kind":"text","text":": "},{"text":"String","kind":"typeIdentifier","preciseIdentifier":"s:SS"},{"text":"?, ","kind":"text"},{"kind":"externalParam","text":"addressFormatMetadata"},{"text":": ","kind":"text"},{"text":"DSAPISettingsMetadata","kind":"typeIdentifier","preciseIdentifier":"c:@M@DocuSignAPI@objc(cs)DSAPISettingsMetadata"},{"kind":"text","text":"?, "},{"text":"allowRegion","kind":"externalParam"},{"text":": ","kind":"text"},{"text":"String","kind":"typeIdentifier","preciseIdentifier":"s:SS"},{"kind":"text","text":"?, "},{"kind":"externalParam","text":"calendarType"},{"text":": ","kind":"text"},{"text":"String","kind":"typeIdentifier","preciseIdentifier":"s:SS"},{"kind":"text","text":"?, "},{"kind":"externalParam","text":"calendarTypeMetadata"},{"kind":"text","text":": "},{"preciseIdentifier":"c:@M@DocuSignAPI@objc(cs)DSAPISettingsMetadata","kind":"typeIdentifier","text":"DSAPISettingsMetadata"},{"text":"?, ","kind":"text"},{"text":"cultureName","kind":"externalParam"},{"kind":"text","text":": "},{"kind":"typeIdentifier","preciseIdentifier":"s:SS","text":"String"},{"text":"?, ","kind":"text"},{"kind":"externalParam","text":"cultureNameMetadata"},{"text":": ","kind":"text"},{"text":"DSAPISettingsMetadata","kind":"typeIdentifier","preciseIdentifier":"c:@M@DocuSignAPI@objc(cs)DSAPISettingsMetadata"},{"text":"?, ","kind":"text"},{"text":"currencyCode","kind":"externalParam"},{"text":": ","kind":"text"},{"preciseIdentifier":"s:SS","text":"String","kind":"typeIdentifier"},{"kind":"text","text":"?, "},{"text":"currencyCodeMetadata","kind":"externalParam"},{"text":": ","kind":"text"},{"kind":"typeIdentifier","text":"DSAPISettingsMetadata","preciseIdentifier":"c:@M@DocuSignAPI@objc(cs)DSAPISettingsMetadata"},{"text":"?, ","kind":"text"},{"text":"currencyNegativeFormat","kind":"externalParam"},{"text":": ","kind":"text"},{"text":"String","kind":"typeIdentifier","preciseIdentifier":"s:SS"},{"text":"?, ","kind":"text"},{"text":"currencyNegativeFormatMetadata","kind":"externalParam"},{"kind":"text","text":": "},{"preciseIdentifier":"c:@M@DocuSignAPI@objc(cs)DSAPISettingsMetadata","text":"DSAPISettingsMetadata","kind":"typeIdentifier"},{"kind":"text","text":"?, "},{"text":"currencyPositiveFormat","kind":"externalParam"},{"text":": ","kind":"text"},{"preciseIdentifier":"s:SS","kind":"typeIdentifier","text":"String"},{"text":"?, ","kind":"text"},{"text":"currencyPositiveFormatMetadata","kind":"externalParam"},{"text":": ","kind":"text"},{"text":"DSAPISettingsMetadata","kind":"typeIdentifier","preciseIdentifier":"c:@M@DocuSignAPI@objc(cs)DSAPISettingsMetadata"},{"text":"?, ","kind":"text"},{"text":"customDateFormat","kind":"externalParam"},{"text":": ","kind":"text"},{"preciseIdentifier":"s:SS","text":"String","kind":"typeIdentifier"},{"kind":"text","text":"?, "},{"text":"customSignDateFormat","kind":"externalParam"},{"kind":"text","text":": "},{"preciseIdentifier":"s:SS","kind":"typeIdentifier","text":"String"},{"text":"?, ","kind":"text"},{"text":"customSignTimeFormat","kind":"externalParam"},{"text":": ","kind":"text"},{"preciseIdentifier":"s:SS","text":"String","kind":"typeIdentifier"},{"text":"?, ","kind":"text"},{"kind":"externalParam","text":"customTimeFormat"},{"text":": ","kind":"text"},{"text":"String","kind":"typeIdentifier","preciseIdentifier":"s:SS"},{"text":"?, ","kind":"text"},{"text":"dateFormat","kind":"externalParam"},{"text":": ","kind":"text"},{"text":"String","preciseIdentifier":"s:SS","kind":"typeIdentifier"},{"kind":"text","text":"?, "},{"text":"dateFormatMetadata","kind":"externalParam"},{"text":": ","kind":"text"},{"text":"DSAPISettingsMetadata","kind":"typeIdentifier","preciseIdentifier":"c:@M@DocuSignAPI@objc(cs)DSAPISettingsMetadata"},{"kind":"text","text":"?, "},{"text":"effectiveAddressFormat","kind":"externalParam"},{"kind":"text","text":": "},{"preciseIdentifier":"s:SS","text":"String","kind":"typeIdentifier"},{"text":"?, ","kind":"text"},{"text":"effectiveCalendarType","kind":"externalParam"},{"text":": ","kind":"text"},{"text":"String","preciseIdentifier":"s:SS","kind":"typeIdentifier"},{"text":"?, ","kind":"text"},{"text":"effectiveCurrencyCode","kind":"externalParam"},{"kind":"text","text":": "},{"text":"String","kind":"typeIdentifier","preciseIdentifier":"s:SS"},{"kind":"text","text":"?, "},{"kind":"externalParam","text":"effectiveCurrencyNegativeFormat"},{"text":": ","kind":"text"},{"kind":"typeIdentifier","preciseIdentifier":"s:SS","text":"String"},{"kind":"text","text":"?, "},{"text":"effectiveCurrencyPositiveFormat","kind":"externalParam"},{"text":": ","kind":"text"},{"text":"String","kind":"typeIdentifier","preciseIdentifier":"s:SS"},{"text":"?, ","kind":"text"},{"text":"effectiveCustomDateFormat","kind":"externalParam"},{"text":": ","kind":"text"},{"kind":"typeIdentifier","text":"String","preciseIdentifier":"s:SS"},{"text":"?, ","kind":"text"},{"text":"effectiveCustomTimeFormat","kind":"externalParam"},{"text":": ","kind":"text"},{"preciseIdentifier":"s:SS","kind":"typeIdentifier","text":"String"},{"text":"?, ","kind":"text"},{"kind":"externalParam","text":"effectiveDateFormat"},{"text":": ","kind":"text"},{"text":"String","kind":"typeIdentifier","preciseIdentifier":"s:SS"},{"kind":"text","text":"?, "},{"text":"effectiveInitialFormat","kind":"externalParam"},{"text":": ","kind":"text"},{"preciseIdentifier":"s:SS","text":"String","kind":"typeIdentifier"},{"kind":"text","text":"?, "},{"text":"effectiveNameFormat","kind":"externalParam"},{"kind":"text","text":": "},{"preciseIdentifier":"s:SS","text":"String","kind":"typeIdentifier"},{"kind":"text","text":"?, "},{"text":"effectiveTimeFormat","kind":"externalParam"},{"text":": ","kind":"text"},{"text":"String","preciseIdentifier":"s:SS","kind":"typeIdentifier"},{"text":"?, ","kind":"text"},{"text":"effectiveTimeZone","kind":"externalParam"},{"kind":"text","text":": "},{"kind":"typeIdentifier","text":"String","preciseIdentifier":"s:SS"},{"text":"?, ","kind":"text"},{"kind":"externalParam","text":"initialFormat"},{"kind":"text","text":": "},{"kind":"typeIdentifier","preciseIdentifier":"s:SS","text":"String"},{"text":"?, ","kind":"text"},{"text":"initialFormatMetadata","kind":"externalParam"},{"kind":"text","text":": "},{"kind":"typeIdentifier","preciseIdentifier":"c:@M@DocuSignAPI@objc(cs)DSAPISettingsMetadata","text":"DSAPISettingsMetadata"},{"text":"?, ","kind":"text"},{"text":"nameFormat","kind":"externalParam"},{"kind":"text","text":": "},{"kind":"typeIdentifier","preciseIdentifier":"s:SS","text":"String"},{"text":"?, ","kind":"text"},{"text":"nameFormatMetadata","kind":"externalParam"},{"kind":"text","text":": "},{"kind":"typeIdentifier","text":"DSAPISettingsMetadata","preciseIdentifier":"c:@M@DocuSignAPI@objc(cs)DSAPISettingsMetadata"},{"text":"?, ","kind":"text"},{"kind":"externalParam","text":"signDateFormat"},{"kind":"text","text":": "},{"text":"String","kind":"typeIdentifier","preciseIdentifier":"s:SS"},{"kind":"text","text":"?, "},{"kind":"externalParam","text":"signDateFormatMetadata"},{"text":": ","kind":"text"},{"kind":"typeIdentifier","preciseIdentifier":"c:@M@DocuSignAPI@objc(cs)DSAPISettingsMetadata","text":"DSAPISettingsMetadata"},{"text":"?, ","kind":"text"},{"text":"signTimeFormat","kind":"externalParam"},{"kind":"text","text":": "},{"preciseIdentifier":"s:SS","text":"String","kind":"typeIdentifier"},{"text":"?, ","kind":"text"},{"text":"signTimeFormatMetadata","kind":"externalParam"},{"text":": ","kind":"text"},{"preciseIdentifier":"c:@M@DocuSignAPI@objc(cs)DSAPISettingsMetadata","text":"DSAPISettingsMetadata","kind":"typeIdentifier"},{"kind":"text","text":"?, "},{"kind":"externalParam","text":"timeFormat"},{"kind":"text","text":": "},{"kind":"typeIdentifier","preciseIdentifier":"s:SS","text":"String"},{"text":"?, ","kind":"text"},{"text":"timeFormatMetadata","kind":"externalParam"},{"text":": ","kind":"text"},{"kind":"typeIdentifier","preciseIdentifier":"c:@M@DocuSignAPI@objc(cs)DSAPISettingsMetadata","text":"DSAPISettingsMetadata"},{"kind":"text","text":"?, "},{"kind":"externalParam","text":"timeZone"},{"text":": ","kind":"text"},{"preciseIdentifier":"s:SS","text":"String","kind":"typeIdentifier"},{"kind":"text","text":"?, "},{"kind":"externalParam","text":"timeZoneMetadata"},{"kind":"text","text":": "},{"text":"DSAPISettingsMetadata","kind":"typeIdentifier","preciseIdentifier":"c:@M@DocuSignAPI@objc(cs)DSAPISettingsMetadata"},{"kind":"text","text":"?)"}],"title":"init(addressFormat:addressFormatMetadata:allowRegion:calendarType:calendarTypeMetadata:cultureName:cultureNameMetadata:currencyCode:currencyCodeMetadata:currencyNegativeFormat:currencyNegativeFormatMetadata:currencyPositiveFormat:currencyPositiveFormatMetadata:customDateFormat:customSignDateFormat:customSignTimeFormat:customTimeFormat:dateFormat:dateFormatMetadata:effectiveAddressFormat:effectiveCalendarType:effectiveCurrencyCode:effectiveCurrencyNegativeFormat:effectiveCurrencyPositiveFormat:effectiveCustomDateFormat:effectiveCustomTimeFormat:effectiveDateFormat:effectiveInitialFormat:effectiveNameFormat:effectiveTimeFormat:effectiveTimeZone:initialFormat:initialFormatMetadata:nameFormat:nameFormatMetadata:signDateFormat:signDateFormatMetadata:signTimeFormat:signTimeFormatMetadata:timeFormat:timeFormatMetadata:timeZone:timeZoneMetadata:)","externalID":"s:11DocuSignAPI17DSAPILocalePolicyV13addressFormat0fG8Metadata11allowRegion12calendarType0klH011cultureName0mnH012currencyCode0opH00o8NegativeG00oqgH00o8PositiveG00orgH0010customDateG00sbtG00sb4TimeG00suG004dateG00vgH0016effectiveAddressG00w8CalendarL00w8CurrencyP00wzqG00wzrG00w6CustomtG00w6CustomuG00wtG00w7InitialG00wnG00wuG00wU4Zone07initialG007initialgH004nameG004namegH004signtG004signtgH004signuG004signugH004timeG004timegH08timeZone08timeZoneH0ACSSSg_AA013DSAPISettingsH0CSgA19_A19_A22_A19_A22_A19_A22_A19_A22_A19_A22_A19_A19_A19_A19_A19_A22_A19_A19_A19_A19_A19_A19_A19_A19_A19_A19_A19_A19_A19_A22_A19_A22_A19_A22_A19_A22_A19_A22_A19_A22_tcfc","role":"symbol","modules":[{"name":"DocuSignAPI"}],"roleHeading":"Initializer","symbolKind":"init"},"primaryContentSections":[{"kind":"declarations","declarations":[{"platforms":["iOS"],"tokens":[{"kind":"keyword","text":"init"},{"kind":"text","text":"("},{"text":"addressFormat","kind":"externalParam"},{"text":": ","kind":"text"},{"kind":"typeIdentifier","preciseIdentifier":"s:SS","text":"String"},{"kind":"text","text":"? = nil, "},{"text":"addressFormatMetadata","kind":"externalParam"},{"text":": ","kind":"text"},{"text":"DSAPISettingsMetadata","identifier":"doc:\/\/com.DocuSign.DocuSIgnAPI\/documentation\/DocuSignAPI\/DSAPISettingsMetadata","preciseIdentifier":"c:@M@DocuSignAPI@objc(cs)DSAPISettingsMetadata","kind":"typeIdentifier"},{"text":"? = nil, ","kind":"text"},{"text":"allowRegion","kind":"externalParam"},{"kind":"text","text":": "},{"preciseIdentifier":"s:SS","text":"String","kind":"typeIdentifier"},{"kind":"text","text":"? = nil, "},{"text":"calendarType","kind":"externalParam"},{"kind":"text","text":": "},{"preciseIdentifier":"s:SS","text":"String","kind":"typeIdentifier"},{"text":"? = nil, ","kind":"text"},{"text":"calendarTypeMetadata","kind":"externalParam"},{"kind":"text","text":": "},{"kind":"typeIdentifier","identifier":"doc:\/\/com.DocuSign.DocuSIgnAPI\/documentation\/DocuSignAPI\/DSAPISettingsMetadata","text":"DSAPISettingsMetadata","preciseIdentifier":"c:@M@DocuSignAPI@objc(cs)DSAPISettingsMetadata"},{"kind":"text","text":"? = nil, "},{"text":"cultureName","kind":"externalParam"},{"kind":"text","text":": "},{"text":"String","kind":"typeIdentifier","preciseIdentifier":"s:SS"},{"text":"? = nil, ","kind":"text"},{"text":"cultureNameMetadata","kind":"externalParam"},{"kind":"text","text":": "},{"kind":"typeIdentifier","preciseIdentifier":"c:@M@DocuSignAPI@objc(cs)DSAPISettingsMetadata","identifier":"doc:\/\/com.DocuSign.DocuSIgnAPI\/documentation\/DocuSignAPI\/DSAPISettingsMetadata","text":"DSAPISettingsMetadata"},{"text":"? = nil, ","kind":"text"},{"text":"currencyCode","kind":"externalParam"},{"kind":"text","text":": "},{"text":"String","preciseIdentifier":"s:SS","kind":"typeIdentifier"},{"text":"? = nil, ","kind":"text"},{"text":"currencyCodeMetadata","kind":"externalParam"},{"kind":"text","text":": "},{"kind":"typeIdentifier","preciseIdentifier":"c:@M@DocuSignAPI@objc(cs)DSAPISettingsMetadata","text":"DSAPISettingsMetadata","identifier":"doc:\/\/com.DocuSign.DocuSIgnAPI\/documentation\/DocuSignAPI\/DSAPISettingsMetadata"},{"kind":"text","text":"? = nil, "},{"text":"currencyNegativeFormat","kind":"externalParam"},{"kind":"text","text":": "},{"kind":"typeIdentifier","preciseIdentifier":"s:SS","text":"String"},{"text":"? = nil, ","kind":"text"},{"text":"currencyNegativeFormatMetadata","kind":"externalParam"},{"kind":"text","text":": "},{"preciseIdentifier":"c:@M@DocuSignAPI@objc(cs)DSAPISettingsMetadata","kind":"typeIdentifier","identifier":"doc:\/\/com.DocuSign.DocuSIgnAPI\/documentation\/DocuSignAPI\/DSAPISettingsMetadata","text":"DSAPISettingsMetadata"},{"kind":"text","text":"? = nil, "},{"kind":"externalParam","text":"currencyPositiveFormat"},{"text":": ","kind":"text"},{"kind":"typeIdentifier","preciseIdentifier":"s:SS","text":"String"},{"text":"? = nil, ","kind":"text"},{"kind":"externalParam","text":"currencyPositiveFormatMetadata"},{"text":": ","kind":"text"},{"preciseIdentifier":"c:@M@DocuSignAPI@objc(cs)DSAPISettingsMetadata","kind":"typeIdentifier","text":"DSAPISettingsMetadata","identifier":"doc:\/\/com.DocuSign.DocuSIgnAPI\/documentation\/DocuSignAPI\/DSAPISettingsMetadata"},{"text":"? = nil, ","kind":"text"},{"kind":"externalParam","text":"customDateFormat"},{"text":": ","kind":"text"},{"kind":"typeIdentifier","text":"String","preciseIdentifier":"s:SS"},{"kind":"text","text":"? = nil, "},{"text":"customSignDateFormat","kind":"externalParam"},{"text":": ","kind":"text"},{"kind":"typeIdentifier","preciseIdentifier":"s:SS","text":"String"},{"text":"? = nil, ","kind":"text"},{"kind":"externalParam","text":"customSignTimeFormat"},{"text":": ","kind":"text"},{"kind":"typeIdentifier","text":"String","preciseIdentifier":"s:SS"},{"text":"? = nil, ","kind":"text"},{"kind":"externalParam","text":"customTimeFormat"},{"kind":"text","text":": "},{"preciseIdentifier":"s:SS","text":"String","kind":"typeIdentifier"},{"text":"? = nil, ","kind":"text"},{"kind":"externalParam","text":"dateFormat"},{"text":": ","kind":"text"},{"text":"String","kind":"typeIdentifier","preciseIdentifier":"s:SS"},{"text":"? = nil, ","kind":"text"},{"text":"dateFormatMetadata","kind":"externalParam"},{"text":": ","kind":"text"},{"preciseIdentifier":"c:@M@DocuSignAPI@objc(cs)DSAPISettingsMetadata","kind":"typeIdentifier","identifier":"doc:\/\/com.DocuSign.DocuSIgnAPI\/documentation\/DocuSignAPI\/DSAPISettingsMetadata","text":"DSAPISettingsMetadata"},{"text":"? = nil, ","kind":"text"},{"text":"effectiveAddressFormat","kind":"externalParam"},{"text":": ","kind":"text"},{"text":"String","preciseIdentifier":"s:SS","kind":"typeIdentifier"},{"text":"? = nil, ","kind":"text"},{"text":"effectiveCalendarType","kind":"externalParam"},{"text":": ","kind":"text"},{"kind":"typeIdentifier","preciseIdentifier":"s:SS","text":"String"},{"kind":"text","text":"? = nil, "},{"kind":"externalParam","text":"effectiveCurrencyCode"},{"kind":"text","text":": "},{"kind":"typeIdentifier","text":"String","preciseIdentifier":"s:SS"},{"kind":"text","text":"? = nil, "},{"text":"effectiveCurrencyNegativeFormat","kind":"externalParam"},{"text":": ","kind":"text"},{"text":"String","kind":"typeIdentifier","preciseIdentifier":"s:SS"},{"kind":"text","text":"? = nil, "},{"text":"effectiveCurrencyPositiveFormat","kind":"externalParam"},{"text":": ","kind":"text"},{"kind":"typeIdentifier","preciseIdentifier":"s:SS","text":"String"},{"text":"? = nil, ","kind":"text"},{"kind":"externalParam","text":"effectiveCustomDateFormat"},{"text":": ","kind":"text"},{"kind":"typeIdentifier","preciseIdentifier":"s:SS","text":"String"},{"text":"? = nil, ","kind":"text"},{"text":"effectiveCustomTimeFormat","kind":"externalParam"},{"kind":"text","text":": "},{"text":"String","preciseIdentifier":"s:SS","kind":"typeIdentifier"},{"kind":"text","text":"? = nil, "},{"kind":"externalParam","text":"effectiveDateFormat"},{"kind":"text","text":": "},{"preciseIdentifier":"s:SS","kind":"typeIdentifier","text":"String"},{"text":"? = nil, ","kind":"text"},{"kind":"externalParam","text":"effectiveInitialFormat"},{"kind":"text","text":": "},{"kind":"typeIdentifier","preciseIdentifier":"s:SS","text":"String"},{"kind":"text","text":"? = nil, "},{"text":"effectiveNameFormat","kind":"externalParam"},{"text":": ","kind":"text"},{"kind":"typeIdentifier","text":"String","preciseIdentifier":"s:SS"},{"text":"? = nil, ","kind":"text"},{"kind":"externalParam","text":"effectiveTimeFormat"},{"text":": ","kind":"text"},{"text":"String","preciseIdentifier":"s:SS","kind":"typeIdentifier"},{"text":"? = nil, ","kind":"text"},{"kind":"externalParam","text":"effectiveTimeZone"},{"text":": ","kind":"text"},{"preciseIdentifier":"s:SS","text":"String","kind":"typeIdentifier"},{"text":"? = nil, ","kind":"text"},{"kind":"externalParam","text":"initialFormat"},{"text":": ","kind":"text"},{"text":"String","kind":"typeIdentifier","preciseIdentifier":"s:SS"},{"kind":"text","text":"? = nil, "},{"text":"initialFormatMetadata","kind":"externalParam"},{"text":": ","kind":"text"},{"preciseIdentifier":"c:@M@DocuSignAPI@objc(cs)DSAPISettingsMetadata","text":"DSAPISettingsMetadata","identifier":"doc:\/\/com.DocuSign.DocuSIgnAPI\/documentation\/DocuSignAPI\/DSAPISettingsMetadata","kind":"typeIdentifier"},{"text":"? = nil, ","kind":"text"},{"kind":"externalParam","text":"nameFormat"},{"kind":"text","text":": "},{"kind":"typeIdentifier","preciseIdentifier":"s:SS","text":"String"},{"kind":"text","text":"? = nil, "},{"kind":"externalParam","text":"nameFormatMetadata"},{"kind":"text","text":": "},{"preciseIdentifier":"c:@M@DocuSignAPI@objc(cs)DSAPISettingsMetadata","identifier":"doc:\/\/com.DocuSign.DocuSIgnAPI\/documentation\/DocuSignAPI\/DSAPISettingsMetadata","text":"DSAPISettingsMetadata","kind":"typeIdentifier"},{"text":"? = nil, ","kind":"text"},{"text":"signDateFormat","kind":"externalParam"},{"kind":"text","text":": "},{"preciseIdentifier":"s:SS","kind":"typeIdentifier","text":"String"},{"text":"? = nil, ","kind":"text"},{"text":"signDateFormatMetadata","kind":"externalParam"},{"text":": ","kind":"text"},{"identifier":"doc:\/\/com.DocuSign.DocuSIgnAPI\/documentation\/DocuSignAPI\/DSAPISettingsMetadata","text":"DSAPISettingsMetadata","kind":"typeIdentifier","preciseIdentifier":"c:@M@DocuSignAPI@objc(cs)DSAPISettingsMetadata"},{"text":"? = nil, ","kind":"text"},{"kind":"externalParam","text":"signTimeFormat"},{"kind":"text","text":": "},{"kind":"typeIdentifier","text":"String","preciseIdentifier":"s:SS"},{"text":"? = nil, ","kind":"text"},{"text":"signTimeFormatMetadata","kind":"externalParam"},{"kind":"text","text":": "},{"identifier":"doc:\/\/com.DocuSign.DocuSIgnAPI\/documentation\/DocuSignAPI\/DSAPISettingsMetadata","kind":"typeIdentifier","text":"DSAPISettingsMetadata","preciseIdentifier":"c:@M@DocuSignAPI@objc(cs)DSAPISettingsMetadata"},{"text":"? = nil, ","kind":"text"},{"text":"timeFormat","kind":"externalParam"},{"text":": ","kind":"text"},{"kind":"typeIdentifier","text":"String","preciseIdentifier":"s:SS"},{"text":"? = nil, ","kind":"text"},{"kind":"externalParam","text":"timeFormatMetadata"},{"kind":"text","text":": "},{"text":"DSAPISettingsMetadata","kind":"typeIdentifier","preciseIdentifier":"c:@M@DocuSignAPI@objc(cs)DSAPISettingsMetadata","identifier":"doc:\/\/com.DocuSign.DocuSIgnAPI\/documentation\/DocuSignAPI\/DSAPISettingsMetadata"},{"text":"? = nil, ","kind":"text"},{"text":"timeZone","kind":"externalParam"},{"kind":"text","text":": "},{"text":"String","preciseIdentifier":"s:SS","kind":"typeIdentifier"},{"text":"? = nil, ","kind":"text"},{"text":"timeZoneMetadata","kind":"externalParam"},{"text":": ","kind":"text"},{"identifier":"doc:\/\/com.DocuSign.DocuSIgnAPI\/documentation\/DocuSignAPI\/DSAPISettingsMetadata","kind":"typeIdentifier","text":"DSAPISettingsMetadata","preciseIdentifier":"c:@M@DocuSignAPI@objc(cs)DSAPISettingsMetadata"},{"text":"? = nil)","kind":"text"}],"languages":["swift"]}]}],"references":{"doc://com.DocuSign.DocuSIgnAPI/documentation/DocuSignAPI/DSAPILocalePolicy/init(addressFormat:addressFormatMetadata:allowRegion:calendarType:calendarTypeMetadata:cultureName:cultureNameMetadata:currencyCode:currencyCodeMetadata:currencyNegativeFormat:currencyNegativeFormatMetadata:currencyPositiveFormat:currencyPositiveFormatMetadata:customDateFormat:customSignDateFormat:customSignTimeFormat:customTimeFormat:dateFormat:dateFormatMetadata:effectiveAddressFormat:effectiveCalendarType:effectiveCurrencyCode:effectiveCurrencyNegativeFormat:effectiveCurrencyPositiveFormat:effectiveCustomDateFormat:effectiveCustomTimeFormat:effectiveDateFormat:effectiveInitialFormat:effectiveNameFormat:effectiveTimeFormat:effectiveTimeZone:initialFormat:initialFormatMetadata:nameFormat:nameFormatMetadata:signDateFormat:signDateFormatMetadata:signTimeFormat:signTimeFormatMetadata:timeFormat:timeFormatMetadata:timeZone:timeZoneMetadata:)":{"type":"topic","url":"\/documentation\/docusignapi\/dsapilocalepolicy\/init(addressformat:addressformatmetadata:allowregion:calendartype:calendartypemetadata:culturename:culturenamemetadata:currencycode:currencycodemetadata:currencynegativeformat:currencynegativeformatmetadata:currencypositiveformat:currencypo-4f49g","abstract":[],"fragments":[{"text":"init","kind":"identifier"},{"text":"(","kind":"text"},{"text":"addressFormat","kind":"externalParam"},{"text":": ","kind":"text"},{"preciseIdentifier":"s:SS","text":"String","kind":"typeIdentifier"},{"text":"?, ","kind":"text"},{"kind":"externalParam","text":"addressFormatMetadata"},{"text":": ","kind":"text"},{"text":"DSAPISettingsMetadata","kind":"typeIdentifier","preciseIdentifier":"c:@M@DocuSignAPI@objc(cs)DSAPISettingsMetadata"},{"kind":"text","text":"?, "},{"text":"allowRegion","kind":"externalParam"},{"text":": ","kind":"text"},{"kind":"typeIdentifier","text":"String","preciseIdentifier":"s:SS"},{"text":"?, ","kind":"text"},{"text":"calendarType","kind":"externalParam"},{"kind":"text","text":": "},{"text":"String","kind":"typeIdentifier","preciseIdentifier":"s:SS"},{"kind":"text","text":"?, "},{"text":"calendarTypeMetadata","kind":"externalParam"},{"text":": ","kind":"text"},{"text":"DSAPISettingsMetadata","kind":"typeIdentifier","preciseIdentifier":"c:@M@DocuSignAPI@objc(cs)DSAPISettingsMetadata"},{"text":"?, ","kind":"text"},{"text":"cultureName","kind":"externalParam"},{"kind":"text","text":": "},{"text":"String","kind":"typeIdentifier","preciseIdentifier":"s:SS"},{"kind":"text","text":"?, "},{"kind":"externalParam","text":"cultureNameMetadata"},{"text":": ","kind":"text"},{"text":"DSAPISettingsMetadata","preciseIdentifier":"c:@M@DocuSignAPI@objc(cs)DSAPISettingsMetadata","kind":"typeIdentifier"},{"text":"?, ","kind":"text"},{"kind":"externalParam","text":"currencyCode"},{"text":": ","kind":"text"},{"preciseIdentifier":"s:SS","text":"String","kind":"typeIdentifier"},{"text":"?, ","kind":"text"},{"text":"currencyCodeMetadata","kind":"externalParam"},{"text":": ","kind":"text"},{"kind":"typeIdentifier","preciseIdentifier":"c:@M@DocuSignAPI@objc(cs)DSAPISettingsMetadata","text":"DSAPISettingsMetadata"},{"kind":"text","text":"?, "},{"text":"currencyNegativeFormat","kind":"externalParam"},{"text":": ","kind":"text"},{"preciseIdentifier":"s:SS","kind":"typeIdentifier","text":"String"},{"kind":"text","text":"?, "},{"text":"currencyNegativeFormatMetadata","kind":"externalParam"},{"kind":"text","text":": "},{"text":"DSAPISettingsMetadata","preciseIdentifier":"c:@M@DocuSignAPI@objc(cs)DSAPISettingsMetadata","kind":"typeIdentifier"},{"kind":"text","text":"?, "},{"text":"currencyPositiveFormat","kind":"externalParam"},{"text":": ","kind":"text"},{"text":"String","kind":"typeIdentifier","preciseIdentifier":"s:SS"},{"text":"?, ","kind":"text"},{"kind":"externalParam","text":"currencyPositiveFormatMetadata"},{"text":": ","kind":"text"},{"preciseIdentifier":"c:@M@DocuSignAPI@objc(cs)DSAPISettingsMetadata","kind":"typeIdentifier","text":"DSAPISettingsMetadata"},{"kind":"text","text":"?, "},{"text":"customDateFormat","kind":"externalParam"},{"text":": ","kind":"text"},{"preciseIdentifier":"s:SS","text":"String","kind":"typeIdentifier"},{"text":"?, ","kind":"text"},{"kind":"externalParam","text":"customSignDateFormat"},{"text":": ","kind":"text"},{"preciseIdentifier":"s:SS","kind":"typeIdentifier","text":"String"},{"text":"?, ","kind":"text"},{"text":"customSignTimeFormat","kind":"externalParam"},{"kind":"text","text":": "},{"kind":"typeIdentifier","text":"String","preciseIdentifier":"s:SS"},{"text":"?, ","kind":"text"},{"kind":"externalParam","text":"customTimeFormat"},{"text":": ","kind":"text"},{"kind":"typeIdentifier","preciseIdentifier":"s:SS","text":"String"},{"text":"?, ","kind":"text"},{"text":"dateFormat","kind":"externalParam"},{"kind":"text","text":": "},{"preciseIdentifier":"s:SS","text":"String","kind":"typeIdentifier"},{"text":"?, ","kind":"text"},{"text":"dateFormatMetadata","kind":"externalParam"},{"kind":"text","text":": "},{"kind":"typeIdentifier","preciseIdentifier":"c:@M@DocuSignAPI@objc(cs)DSAPISettingsMetadata","text":"DSAPISettingsMetadata"},{"kind":"text","text":"?, "},{"text":"effectiveAddressFormat","kind":"externalParam"},{"kind":"text","text":": "},{"text":"String","kind":"typeIdentifier","preciseIdentifier":"s:SS"},{"kind":"text","text":"?, "},{"text":"effectiveCalendarType","kind":"externalParam"},{"text":": ","kind":"text"},{"text":"String","kind":"typeIdentifier","preciseIdentifier":"s:SS"},{"text":"?, ","kind":"text"},{"text":"effectiveCurrencyCode","kind":"externalParam"},{"kind":"text","text":": "},{"preciseIdentifier":"s:SS","text":"String","kind":"typeIdentifier"},{"kind":"text","text":"?, "},{"text":"effectiveCurrencyNegativeFormat","kind":"externalParam"},{"text":": ","kind":"text"},{"kind":"typeIdentifier","preciseIdentifier":"s:SS","text":"String"},{"text":"?, ","kind":"text"},{"text":"effectiveCurrencyPositiveFormat","kind":"externalParam"},{"text":": ","kind":"text"},{"text":"String","preciseIdentifier":"s:SS","kind":"typeIdentifier"},{"kind":"text","text":"?, "},{"text":"effectiveCustomDateFormat","kind":"externalParam"},{"text":": ","kind":"text"},{"text":"String","preciseIdentifier":"s:SS","kind":"typeIdentifier"},{"kind":"text","text":"?, "},{"text":"effectiveCustomTimeFormat","kind":"externalParam"},{"text":": ","kind":"text"},{"preciseIdentifier":"s:SS","kind":"typeIdentifier","text":"String"},{"text":"?, ","kind":"text"},{"text":"effectiveDateFormat","kind":"externalParam"},{"text":": ","kind":"text"},{"kind":"typeIdentifier","text":"String","preciseIdentifier":"s:SS"},{"kind":"text","text":"?, "},{"text":"effectiveInitialFormat","kind":"externalParam"},{"kind":"text","text":": "},{"preciseIdentifier":"s:SS","text":"String","kind":"typeIdentifier"},{"kind":"text","text":"?, "},{"text":"effectiveNameFormat","kind":"externalParam"},{"kind":"text","text":": "},{"preciseIdentifier":"s:SS","kind":"typeIdentifier","text":"String"},{"text":"?, ","kind":"text"},{"kind":"externalParam","text":"effectiveTimeFormat"},{"text":": ","kind":"text"},{"preciseIdentifier":"s:SS","kind":"typeIdentifier","text":"String"},{"text":"?, ","kind":"text"},{"kind":"externalParam","text":"effectiveTimeZone"},{"text":": ","kind":"text"},{"preciseIdentifier":"s:SS","kind":"typeIdentifier","text":"String"},{"text":"?, ","kind":"text"},{"text":"initialFormat","kind":"externalParam"},{"text":": ","kind":"text"},{"text":"String","kind":"typeIdentifier","preciseIdentifier":"s:SS"},{"text":"?, ","kind":"text"},{"kind":"externalParam","text":"initialFormatMetadata"},{"kind":"text","text":": "},{"preciseIdentifier":"c:@M@DocuSignAPI@objc(cs)DSAPISettingsMetadata","text":"DSAPISettingsMetadata","kind":"typeIdentifier"},{"text":"?, ","kind":"text"},{"text":"nameFormat","kind":"externalParam"},{"kind":"text","text":": "},{"preciseIdentifier":"s:SS","text":"String","kind":"typeIdentifier"},{"text":"?, ","kind":"text"},{"text":"nameFormatMetadata","kind":"externalParam"},{"kind":"text","text":": "},{"text":"DSAPISettingsMetadata","kind":"typeIdentifier","preciseIdentifier":"c:@M@DocuSignAPI@objc(cs)DSAPISettingsMetadata"},{"kind":"text","text":"?, "},{"text":"signDateFormat","kind":"externalParam"},{"kind":"text","text":": "},{"preciseIdentifier":"s:SS","kind":"typeIdentifier","text":"String"},{"text":"?, ","kind":"text"},{"text":"signDateFormatMetadata","kind":"externalParam"},{"kind":"text","text":": "},{"text":"DSAPISettingsMetadata","kind":"typeIdentifier","preciseIdentifier":"c:@M@DocuSignAPI@objc(cs)DSAPISettingsMetadata"},{"kind":"text","text":"?, "},{"text":"signTimeFormat","kind":"externalParam"},{"text":": ","kind":"text"},{"text":"String","preciseIdentifier":"s:SS","kind":"typeIdentifier"},{"kind":"text","text":"?, "},{"text":"signTimeFormatMetadata","kind":"externalParam"},{"text":": ","kind":"text"},{"kind":"typeIdentifier","text":"DSAPISettingsMetadata","preciseIdentifier":"c:@M@DocuSignAPI@objc(cs)DSAPISettingsMetadata"},{"text":"?, ","kind":"text"},{"text":"timeFormat","kind":"externalParam"},{"text":": ","kind":"text"},{"kind":"typeIdentifier","text":"String","preciseIdentifier":"s:SS"},{"text":"?, ","kind":"text"},{"kind":"externalParam","text":"timeFormatMetadata"},{"text":": ","kind":"text"},{"preciseIdentifier":"c:@M@DocuSignAPI@objc(cs)DSAPISettingsMetadata","kind":"typeIdentifier","text":"DSAPISettingsMetadata"},{"text":"?, ","kind":"text"},{"text":"timeZone","kind":"externalParam"},{"text":": ","kind":"text"},{"kind":"typeIdentifier","text":"String","preciseIdentifier":"s:SS"},{"text":"?, ","kind":"text"},{"kind":"externalParam","text":"timeZoneMetadata"},{"kind":"text","text":": "},{"kind":"typeIdentifier","preciseIdentifier":"c:@M@DocuSignAPI@objc(cs)DSAPISettingsMetadata","text":"DSAPISettingsMetadata"},{"kind":"text","text":"?)"}],"kind":"symbol","identifier":"doc:\/\/com.DocuSign.DocuSIgnAPI\/documentation\/DocuSignAPI\/DSAPILocalePolicy\/init(addressFormat:addressFormatMetadata:allowRegion:calendarType:calendarTypeMetadata:cultureName:cultureNameMetadata:currencyCode:currencyCodeMetadata:currencyNegativeFormat:currencyNegativeFormatMetadata:currencyPositiveFormat:currencyPositiveFormatMetadata:customDateFormat:customSignDateFormat:customSignTimeFormat:customTimeFormat:dateFormat:dateFormatMetadata:effectiveAddressFormat:effectiveCalendarType:effectiveCurrencyCode:effectiveCurrencyNegativeFormat:effectiveCurrencyPositiveFormat:effectiveCustomDateFormat:effectiveCustomTimeFormat:effectiveDateFormat:effectiveInitialFormat:effectiveNameFormat:effectiveTimeFormat:effectiveTimeZone:initialFormat:initialFormatMetadata:nameFormat:nameFormatMetadata:signDateFormat:signDateFormatMetadata:signTimeFormat:signTimeFormatMetadata:timeFormat:timeFormatMetadata:timeZone:timeZoneMetadata:)","role":"symbol","title":"init(addressFormat:addressFormatMetadata:allowRegion:calendarType:calendarTypeMetadata:cultureName:cultureNameMetadata:currencyCode:currencyCodeMetadata:currencyNegativeFormat:currencyNegativeFormatMetadata:currencyPositiveFormat:currencyPositiveFormatMetadata:customDateFormat:customSignDateFormat:customSignTimeFormat:customTimeFormat:dateFormat:dateFormatMetadata:effectiveAddressFormat:effectiveCalendarType:effectiveCurrencyCode:effectiveCurrencyNegativeFormat:effectiveCurrencyPositiveFormat:effectiveCustomDateFormat:effectiveCustomTimeFormat:effectiveDateFormat:effectiveInitialFormat:effectiveNameFormat:effectiveTimeFormat:effectiveTimeZone:initialFormat:initialFormatMetadata:nameFormat:nameFormatMetadata:signDateFormat:signDateFormatMetadata:signTimeFormat:signTimeFormatMetadata:timeFormat:timeFormatMetadata:timeZone:timeZoneMetadata:)"},"doc://com.DocuSign.DocuSIgnAPI/documentation/DocuSignAPI":{"kind":"symbol","type":"topic","role":"collection","url":"\/documentation\/docusignapi","abstract":[],"title":"DocuSignAPI","identifier":"doc:\/\/com.DocuSign.DocuSIgnAPI\/documentation\/DocuSignAPI"},"doc://com.DocuSign.DocuSIgnAPI/documentation/DocuSignAPI/DSAPILocalePolicy":{"url":"\/documentation\/docusignapi\/dsapilocalepolicy","identifier":"doc:\/\/com.DocuSign.DocuSIgnAPI\/documentation\/DocuSignAPI\/DSAPILocalePolicy","title":"DSAPILocalePolicy","role":"symbol","abstract":[],"fragments":[{"text":"struct","kind":"keyword"},{"kind":"text","text":" "},{"kind":"identifier","text":"DSAPILocalePolicy"}],"navigatorTitle":[{"text":"DSAPILocalePolicy","kind":"identifier"}],"kind":"symbol","type":"topic"},"doc://com.DocuSign.DocuSIgnAPI/documentation/DocuSignAPI/DSAPISettingsMetadata":{"navigatorTitle":[{"kind":"identifier","text":"DSAPISettingsMetadata"}],"role":"symbol","abstract":[{"type":"text","text":"Metadata that indicates whether a property is editable and describes setting-specific options."}],"title":"DSAPISettingsMetadata","kind":"symbol","url":"\/documentation\/docusignapi\/dsapisettingsmetadata","type":"topic","fragments":[{"text":"class","kind":"keyword"},{"text":" ","kind":"text"},{"text":"DSAPISettingsMetadata","kind":"identifier"}],"identifier":"doc:\/\/com.DocuSign.DocuSIgnAPI\/documentation\/DocuSignAPI\/DSAPISettingsMetadata"}},"variantOverrides":[{"patch":[{"value":"DSAPISettingsMetadata","op":"replace","path":"\/references\/doc:~1~1com.DocuSign.DocuSIgnAPI~1documentation~1DocuSignAPI~1DSAPISettingsMetadata\/title"},{"op":"replace","path":"\/references\/doc:~1~1com.DocuSign.DocuSIgnAPI~1documentation~1DocuSignAPI~1DSAPISettingsMetadata\/fragments","value":[{"text":"DSAPISettingsMetadata","kind":"identifier"}]}],"traits":[{"interfaceLanguage":"occ"}]}]}