{"hierarchy":{"paths":[["doc:\/\/com.DocuSign.DocuSIgnAPI\/documentation\/DocuSignAPI","doc:\/\/com.DocuSign.DocuSIgnAPI\/documentation\/DocuSignAPI\/DSAPITabAccountSettings"]]},"sections":[],"primaryContentSections":[{"kind":"declarations","declarations":[{"languages":["swift"],"tokens":[{"text":"init","kind":"keyword"},{"kind":"text","text":"("},{"text":"allowTabOrder","kind":"externalParam"},{"kind":"text","text":": "},{"kind":"typeIdentifier","preciseIdentifier":"s:Sb","text":"Bool"},{"text":" = false, ","kind":"text"},{"text":"allowTabOrderMetadata","kind":"externalParam"},{"kind":"text","text":": "},{"identifier":"doc:\/\/com.DocuSign.DocuSIgnAPI\/documentation\/DocuSignAPI\/DSAPISettingsMetadata","text":"DSAPISettingsMetadata","preciseIdentifier":"c:@M@DocuSignAPI@objc(cs)DSAPISettingsMetadata","kind":"typeIdentifier"},{"text":"? = nil, ","kind":"text"},{"text":"approveDeclineTabsEnabled","kind":"externalParam"},{"text":": ","kind":"text"},{"text":"Bool","kind":"typeIdentifier","preciseIdentifier":"s:Sb"},{"text":" = false, ","kind":"text"},{"text":"approveDeclineTabsMetadata","kind":"externalParam"},{"kind":"text","text":": "},{"identifier":"doc:\/\/com.DocuSign.DocuSIgnAPI\/documentation\/DocuSignAPI\/DSAPISettingsMetadata","preciseIdentifier":"c:@M@DocuSignAPI@objc(cs)DSAPISettingsMetadata","text":"DSAPISettingsMetadata","kind":"typeIdentifier"},{"text":"? = nil, ","kind":"text"},{"text":"calculatedFieldsEnabled","kind":"externalParam"},{"text":": ","kind":"text"},{"kind":"typeIdentifier","preciseIdentifier":"s:Sb","text":"Bool"},{"kind":"text","text":" = false, "},{"kind":"externalParam","text":"calculatedFieldsMetadata"},{"text":": ","kind":"text"},{"kind":"typeIdentifier","preciseIdentifier":"c:@M@DocuSignAPI@objc(cs)DSAPISettingsMetadata","identifier":"doc:\/\/com.DocuSign.DocuSIgnAPI\/documentation\/DocuSignAPI\/DSAPISettingsMetadata","text":"DSAPISettingsMetadata"},{"kind":"text","text":"? = nil, "},{"text":"checkboxTabsEnabled","kind":"externalParam"},{"text":": ","kind":"text"},{"preciseIdentifier":"s:Sb","text":"Bool","kind":"typeIdentifier"},{"text":" = false, ","kind":"text"},{"text":"checkBoxTabsMetadata","kind":"externalParam"},{"kind":"text","text":": "},{"preciseIdentifier":"c:@M@DocuSignAPI@objc(cs)DSAPISettingsMetadata","kind":"typeIdentifier","identifier":"doc:\/\/com.DocuSign.DocuSIgnAPI\/documentation\/DocuSignAPI\/DSAPISettingsMetadata","text":"DSAPISettingsMetadata"},{"text":"? = nil, ","kind":"text"},{"text":"currencyTabsEnabled","kind":"externalParam"},{"text":": ","kind":"text"},{"preciseIdentifier":"s:Sb","text":"Bool","kind":"typeIdentifier"},{"text":" = false, ","kind":"text"},{"text":"currencyTabsMetadata","kind":"externalParam"},{"kind":"text","text":": "},{"text":"DSAPISettingsMetadata","identifier":"doc:\/\/com.DocuSign.DocuSIgnAPI\/documentation\/DocuSignAPI\/DSAPISettingsMetadata","kind":"typeIdentifier","preciseIdentifier":"c:@M@DocuSignAPI@objc(cs)DSAPISettingsMetadata"},{"kind":"text","text":"? = nil, "},{"kind":"externalParam","text":"dataFieldRegexEnabled"},{"text":": ","kind":"text"},{"preciseIdentifier":"s:Sb","kind":"typeIdentifier","text":"Bool"},{"kind":"text","text":" = false, "},{"text":"dataFieldRegexMetadata","kind":"externalParam"},{"text":": ","kind":"text"},{"preciseIdentifier":"c:@M@DocuSignAPI@objc(cs)DSAPISettingsMetadata","identifier":"doc:\/\/com.DocuSign.DocuSIgnAPI\/documentation\/DocuSignAPI\/DSAPISettingsMetadata","kind":"typeIdentifier","text":"DSAPISettingsMetadata"},{"kind":"text","text":"? = nil, "},{"kind":"externalParam","text":"dataFieldSizeEnabled"},{"kind":"text","text":": "},{"text":"Bool","kind":"typeIdentifier","preciseIdentifier":"s:Sb"},{"kind":"text","text":" = false, "},{"kind":"externalParam","text":"dataFieldSizeMetadata"},{"kind":"text","text":": "},{"preciseIdentifier":"c:@M@DocuSignAPI@objc(cs)DSAPISettingsMetadata","kind":"typeIdentifier","text":"DSAPISettingsMetadata","identifier":"doc:\/\/com.DocuSign.DocuSIgnAPI\/documentation\/DocuSignAPI\/DSAPISettingsMetadata"},{"kind":"text","text":"? = nil, "},{"text":"drawTabsEnabled","kind":"externalParam"},{"kind":"text","text":": "},{"text":"Bool","preciseIdentifier":"s:Sb","kind":"typeIdentifier"},{"text":" = false, ","kind":"text"},{"text":"drawTabsMetadata","kind":"externalParam"},{"text":": ","kind":"text"},{"text":"DSAPISettingsMetadata","preciseIdentifier":"c:@M@DocuSignAPI@objc(cs)DSAPISettingsMetadata","identifier":"doc:\/\/com.DocuSign.DocuSIgnAPI\/documentation\/DocuSignAPI\/DSAPISettingsMetadata","kind":"typeIdentifier"},{"text":"? = nil, ","kind":"text"},{"kind":"externalParam","text":"firstLastEmailTabsEnabled"},{"kind":"text","text":": "},{"kind":"typeIdentifier","preciseIdentifier":"s:Sb","text":"Bool"},{"kind":"text","text":" = false, "},{"text":"firstLastEmailTabsMetadata","kind":"externalParam"},{"kind":"text","text":": "},{"kind":"typeIdentifier","preciseIdentifier":"c:@M@DocuSignAPI@objc(cs)DSAPISettingsMetadata","text":"DSAPISettingsMetadata","identifier":"doc:\/\/com.DocuSign.DocuSIgnAPI\/documentation\/DocuSignAPI\/DSAPISettingsMetadata"},{"text":"? = nil, ","kind":"text"},{"text":"listTabsEnabled","kind":"externalParam"},{"text":": ","kind":"text"},{"preciseIdentifier":"s:Sb","kind":"typeIdentifier","text":"Bool"},{"kind":"text","text":" = false, "},{"text":"listTabsMetadata","kind":"externalParam"},{"kind":"text","text":": "},{"kind":"typeIdentifier","preciseIdentifier":"c:@M@DocuSignAPI@objc(cs)DSAPISettingsMetadata","text":"DSAPISettingsMetadata","identifier":"doc:\/\/com.DocuSign.DocuSIgnAPI\/documentation\/DocuSignAPI\/DSAPISettingsMetadata"},{"text":"? = nil, ","kind":"text"},{"text":"noteTabsEnabled","kind":"externalParam"},{"text":": ","kind":"text"},{"kind":"typeIdentifier","text":"Bool","preciseIdentifier":"s:Sb"},{"text":" = false, ","kind":"text"},{"kind":"externalParam","text":"noteTabsMetadata"},{"text":": ","kind":"text"},{"text":"DSAPISettingsMetadata","preciseIdentifier":"c:@M@DocuSignAPI@objc(cs)DSAPISettingsMetadata","kind":"typeIdentifier","identifier":"doc:\/\/com.DocuSign.DocuSIgnAPI\/documentation\/DocuSignAPI\/DSAPISettingsMetadata"},{"text":"? = nil, ","kind":"text"},{"text":"prefillTabsEnabled","kind":"externalParam"},{"text":": ","kind":"text"},{"preciseIdentifier":"s:Sb","kind":"typeIdentifier","text":"Bool"},{"kind":"text","text":" = false, "},{"text":"prefillTabsMetadata","kind":"externalParam"},{"kind":"text","text":": "},{"text":"DSAPISettingsMetadata","identifier":"doc:\/\/com.DocuSign.DocuSIgnAPI\/documentation\/DocuSignAPI\/DSAPISettingsMetadata","preciseIdentifier":"c:@M@DocuSignAPI@objc(cs)DSAPISettingsMetadata","kind":"typeIdentifier"},{"kind":"text","text":"? = nil, "},{"text":"radioTabsEnabled","kind":"externalParam"},{"kind":"text","text":": "},{"kind":"typeIdentifier","text":"Bool","preciseIdentifier":"s:Sb"},{"kind":"text","text":" = false, "},{"kind":"externalParam","text":"radioTabsMetadata"},{"kind":"text","text":": "},{"kind":"typeIdentifier","text":"DSAPISettingsMetadata","identifier":"doc:\/\/com.DocuSign.DocuSIgnAPI\/documentation\/DocuSignAPI\/DSAPISettingsMetadata","preciseIdentifier":"c:@M@DocuSignAPI@objc(cs)DSAPISettingsMetadata"},{"kind":"text","text":"? = nil, "},{"kind":"externalParam","text":"savingCustomTabsEnabled"},{"text":": ","kind":"text"},{"text":"Bool","preciseIdentifier":"s:Sb","kind":"typeIdentifier"},{"kind":"text","text":" = false, "},{"text":"savingCustomTabsMetadata","kind":"externalParam"},{"text":": ","kind":"text"},{"identifier":"doc:\/\/com.DocuSign.DocuSIgnAPI\/documentation\/DocuSignAPI\/DSAPISettingsMetadata","text":"DSAPISettingsMetadata","kind":"typeIdentifier","preciseIdentifier":"c:@M@DocuSignAPI@objc(cs)DSAPISettingsMetadata"},{"kind":"text","text":"? = nil, "},{"text":"senderToChangeTabAssignmentsEnabled","kind":"externalParam"},{"kind":"text","text":": "},{"preciseIdentifier":"s:Sb","text":"Bool","kind":"typeIdentifier"},{"text":" = false, ","kind":"text"},{"text":"senderToChangeTabAssignmentsMetadata","kind":"externalParam"},{"text":": ","kind":"text"},{"preciseIdentifier":"c:@M@DocuSignAPI@objc(cs)DSAPISettingsMetadata","identifier":"doc:\/\/com.DocuSign.DocuSIgnAPI\/documentation\/DocuSignAPI\/DSAPISettingsMetadata","kind":"typeIdentifier","text":"DSAPISettingsMetadata"},{"kind":"text","text":"? = nil, "},{"text":"sharedCustomTabsEnabled","kind":"externalParam"},{"kind":"text","text":": "},{"preciseIdentifier":"s:Sb","text":"Bool","kind":"typeIdentifier"},{"kind":"text","text":" = false, "},{"text":"sharedCustomTabsMetadata","kind":"externalParam"},{"kind":"text","text":": "},{"preciseIdentifier":"c:@M@DocuSignAPI@objc(cs)DSAPISettingsMetadata","kind":"typeIdentifier","identifier":"doc:\/\/com.DocuSign.DocuSIgnAPI\/documentation\/DocuSignAPI\/DSAPISettingsMetadata","text":"DSAPISettingsMetadata"},{"kind":"text","text":"? = nil, "},{"kind":"externalParam","text":"tabDataLabelEnabled"},{"text":": ","kind":"text"},{"text":"Bool","kind":"typeIdentifier","preciseIdentifier":"s:Sb"},{"kind":"text","text":" = false, "},{"kind":"externalParam","text":"tabDataLabelMetadata"},{"text":": ","kind":"text"},{"identifier":"doc:\/\/com.DocuSign.DocuSIgnAPI\/documentation\/DocuSignAPI\/DSAPISettingsMetadata","kind":"typeIdentifier","preciseIdentifier":"c:@M@DocuSignAPI@objc(cs)DSAPISettingsMetadata","text":"DSAPISettingsMetadata"},{"text":"? = nil, ","kind":"text"},{"kind":"externalParam","text":"tabLocationEnabled"},{"text":": ","kind":"text"},{"preciseIdentifier":"s:Sb","text":"Bool","kind":"typeIdentifier"},{"text":" = false, ","kind":"text"},{"text":"tabLocationMetadata","kind":"externalParam"},{"text":": ","kind":"text"},{"text":"DSAPISettingsMetadata","identifier":"doc:\/\/com.DocuSign.DocuSIgnAPI\/documentation\/DocuSignAPI\/DSAPISettingsMetadata","kind":"typeIdentifier","preciseIdentifier":"c:@M@DocuSignAPI@objc(cs)DSAPISettingsMetadata"},{"text":"? = nil, ","kind":"text"},{"text":"tabLockingEnabled","kind":"externalParam"},{"text":": ","kind":"text"},{"text":"Bool","preciseIdentifier":"s:Sb","kind":"typeIdentifier"},{"kind":"text","text":" = false, "},{"text":"tabLockingMetadata","kind":"externalParam"},{"text":": ","kind":"text"},{"preciseIdentifier":"c:@M@DocuSignAPI@objc(cs)DSAPISettingsMetadata","text":"DSAPISettingsMetadata","kind":"typeIdentifier","identifier":"doc:\/\/com.DocuSign.DocuSIgnAPI\/documentation\/DocuSignAPI\/DSAPISettingsMetadata"},{"text":"? = nil, ","kind":"text"},{"text":"tabScaleEnabled","kind":"externalParam"},{"kind":"text","text":": "},{"kind":"typeIdentifier","preciseIdentifier":"s:Sb","text":"Bool"},{"text":" = false, ","kind":"text"},{"kind":"externalParam","text":"tabScaleMetadata"},{"text":": ","kind":"text"},{"identifier":"doc:\/\/com.DocuSign.DocuSIgnAPI\/documentation\/DocuSignAPI\/DSAPISettingsMetadata","text":"DSAPISettingsMetadata","preciseIdentifier":"c:@M@DocuSignAPI@objc(cs)DSAPISettingsMetadata","kind":"typeIdentifier"},{"kind":"text","text":"? = nil, "},{"kind":"externalParam","text":"tabTextFormattingEnabled"},{"kind":"text","text":": "},{"kind":"typeIdentifier","text":"Bool","preciseIdentifier":"s:Sb"},{"text":" = false, ","kind":"text"},{"text":"tabTextFormattingMetadata","kind":"externalParam"},{"text":": ","kind":"text"},{"kind":"typeIdentifier","identifier":"doc:\/\/com.DocuSign.DocuSIgnAPI\/documentation\/DocuSignAPI\/DSAPISettingsMetadata","text":"DSAPISettingsMetadata","preciseIdentifier":"c:@M@DocuSignAPI@objc(cs)DSAPISettingsMetadata"},{"kind":"text","text":"? = nil, "},{"text":"textTabsEnabled","kind":"externalParam"},{"kind":"text","text":": "},{"text":"Bool","kind":"typeIdentifier","preciseIdentifier":"s:Sb"},{"text":" = false, ","kind":"text"},{"text":"textTabsMetadata","kind":"externalParam"},{"kind":"text","text":": "},{"preciseIdentifier":"c:@M@DocuSignAPI@objc(cs)DSAPISettingsMetadata","identifier":"doc:\/\/com.DocuSign.DocuSIgnAPI\/documentation\/DocuSignAPI\/DSAPISettingsMetadata","kind":"typeIdentifier","text":"DSAPISettingsMetadata"},{"text":"? = nil)","kind":"text"}],"platforms":["iOS"]}]}],"variants":[{"paths":["\/documentation\/docusignapi\/dsapitabaccountsettings\/init(allowtaborder:allowtabordermetadata:approvedeclinetabsenabled:approvedeclinetabsmetadata:calculatedfieldsenabled:calculatedfieldsmetadata:checkboxtabsenabled:checkboxtabsmetadata:currencytabsenabled:currencytabsmetadata:datafieldregexe-98kwl"],"traits":[{"interfaceLanguage":"swift"}]}],"schemaVersion":{"minor":3,"patch":0,"major":0},"kind":"symbol","identifier":{"url":"doc:\/\/com.DocuSign.DocuSIgnAPI\/documentation\/DocuSignAPI\/DSAPITabAccountSettings\/init(allowTabOrder:allowTabOrderMetadata:approveDeclineTabsEnabled:approveDeclineTabsMetadata:calculatedFieldsEnabled:calculatedFieldsMetadata:checkboxTabsEnabled:checkBoxTabsMetadata:currencyTabsEnabled:currencyTabsMetadata:dataFieldRegexEnabled:dataFieldRegexMetadata:dataFieldSizeEnabled:dataFieldSizeMetadata:drawTabsEnabled:drawTabsMetadata:firstLastEmailTabsEnabled:firstLastEmailTabsMetadata:listTabsEnabled:listTabsMetadata:noteTabsEnabled:noteTabsMetadata:prefillTabsEnabled:prefillTabsMetadata:radioTabsEnabled:radioTabsMetadata:savingCustomTabsEnabled:savingCustomTabsMetadata:senderToChangeTabAssignmentsEnabled:senderToChangeTabAssignmentsMetadata:sharedCustomTabsEnabled:sharedCustomTabsMetadata:tabDataLabelEnabled:tabDataLabelMetadata:tabLocationEnabled:tabLocationMetadata:tabLockingEnabled:tabLockingMetadata:tabScaleEnabled:tabScaleMetadata:tabTextFormattingEnabled:tabTextFormattingMetadata:textTabsEnabled:textTabsMetadata:)","interfaceLanguage":"swift"},"metadata":{"title":"init(allowTabOrder:allowTabOrderMetadata:approveDeclineTabsEnabled:approveDeclineTabsMetadata:calculatedFieldsEnabled:calculatedFieldsMetadata:checkboxTabsEnabled:checkBoxTabsMetadata:currencyTabsEnabled:currencyTabsMetadata:dataFieldRegexEnabled:dataFieldRegexMetadata:dataFieldSizeEnabled:dataFieldSizeMetadata:drawTabsEnabled:drawTabsMetadata:firstLastEmailTabsEnabled:firstLastEmailTabsMetadata:listTabsEnabled:listTabsMetadata:noteTabsEnabled:noteTabsMetadata:prefillTabsEnabled:prefillTabsMetadata:radioTabsEnabled:radioTabsMetadata:savingCustomTabsEnabled:savingCustomTabsMetadata:senderToChangeTabAssignmentsEnabled:senderToChangeTabAssignmentsMetadata:sharedCustomTabsEnabled:sharedCustomTabsMetadata:tabDataLabelEnabled:tabDataLabelMetadata:tabLocationEnabled:tabLocationMetadata:tabLockingEnabled:tabLockingMetadata:tabScaleEnabled:tabScaleMetadata:tabTextFormattingEnabled:tabTextFormattingMetadata:textTabsEnabled:textTabsMetadata:)","externalID":"s:11DocuSignAPI23DSAPITabAccountSettingsV13allowTabOrder0ghI8Metadata25approveDeclineTabsEnabled0klmJ0016calculatedFieldsN00opJ008checkboxmN008checkBoxmJ008currencymN00tmJ0014dataFieldRegexN00uvwJ00uv4SizeN00uvxJ004drawmN00ymJ0014firstLastEmailmN00z9LastEmailmJ004listmN004listmJ004notemN004notemJ007prefillmN007prefillmJ005radiomN005radiomJ0012savingCustommN0012savingCustommJ0014senderToChangeh11AssignmentsN0014senderToChangeh11AssignmentsJ0012sharedCustommN0012sharedCustommJ0012tabDataLabelN0012tabDataLabelJ0011tabLocationN0011tabLocationJ0010tabLockingN0010tabLockingJ008tabScaleN008tabScaleJ0017tabTextFormattingN0017tabTextFormattingJ004textmN004textmJ0ACSb_AA013DSAPISettingsJ0CSgSbA22_SbA22_SbA22_SbA22_SbA22_SbA22_SbA22_SbA22_SbA22_SbA22_SbA22_SbA22_SbA22_SbA22_SbA22_SbA22_SbA22_SbA22_SbA22_SbA22_SbA22_tcfc","symbolKind":"init","roleHeading":"Initializer","fragments":[{"text":"init","kind":"identifier"},{"kind":"text","text":"("},{"text":"allowTabOrder","kind":"externalParam"},{"text":": ","kind":"text"},{"text":"Bool","kind":"typeIdentifier","preciseIdentifier":"s:Sb"},{"text":", ","kind":"text"},{"text":"allowTabOrderMetadata","kind":"externalParam"},{"kind":"text","text":": "},{"text":"DSAPISettingsMetadata","kind":"typeIdentifier","preciseIdentifier":"c:@M@DocuSignAPI@objc(cs)DSAPISettingsMetadata"},{"kind":"text","text":"?, "},{"text":"approveDeclineTabsEnabled","kind":"externalParam"},{"text":": ","kind":"text"},{"preciseIdentifier":"s:Sb","text":"Bool","kind":"typeIdentifier"},{"text":", ","kind":"text"},{"text":"approveDeclineTabsMetadata","kind":"externalParam"},{"text":": ","kind":"text"},{"text":"DSAPISettingsMetadata","kind":"typeIdentifier","preciseIdentifier":"c:@M@DocuSignAPI@objc(cs)DSAPISettingsMetadata"},{"kind":"text","text":"?, "},{"text":"calculatedFieldsEnabled","kind":"externalParam"},{"kind":"text","text":": "},{"preciseIdentifier":"s:Sb","kind":"typeIdentifier","text":"Bool"},{"kind":"text","text":", "},{"text":"calculatedFieldsMetadata","kind":"externalParam"},{"kind":"text","text":": "},{"text":"DSAPISettingsMetadata","kind":"typeIdentifier","preciseIdentifier":"c:@M@DocuSignAPI@objc(cs)DSAPISettingsMetadata"},{"text":"?, ","kind":"text"},{"text":"checkboxTabsEnabled","kind":"externalParam"},{"kind":"text","text":": "},{"kind":"typeIdentifier","preciseIdentifier":"s:Sb","text":"Bool"},{"text":", ","kind":"text"},{"kind":"externalParam","text":"checkBoxTabsMetadata"},{"kind":"text","text":": "},{"kind":"typeIdentifier","preciseIdentifier":"c:@M@DocuSignAPI@objc(cs)DSAPISettingsMetadata","text":"DSAPISettingsMetadata"},{"text":"?, ","kind":"text"},{"text":"currencyTabsEnabled","kind":"externalParam"},{"text":": ","kind":"text"},{"text":"Bool","kind":"typeIdentifier","preciseIdentifier":"s:Sb"},{"kind":"text","text":", "},{"text":"currencyTabsMetadata","kind":"externalParam"},{"text":": ","kind":"text"},{"text":"DSAPISettingsMetadata","kind":"typeIdentifier","preciseIdentifier":"c:@M@DocuSignAPI@objc(cs)DSAPISettingsMetadata"},{"kind":"text","text":"?, "},{"text":"dataFieldRegexEnabled","kind":"externalParam"},{"kind":"text","text":": "},{"text":"Bool","kind":"typeIdentifier","preciseIdentifier":"s:Sb"},{"text":", ","kind":"text"},{"kind":"externalParam","text":"dataFieldRegexMetadata"},{"text":": ","kind":"text"},{"kind":"typeIdentifier","preciseIdentifier":"c:@M@DocuSignAPI@objc(cs)DSAPISettingsMetadata","text":"DSAPISettingsMetadata"},{"text":"?, ","kind":"text"},{"kind":"externalParam","text":"dataFieldSizeEnabled"},{"text":": ","kind":"text"},{"preciseIdentifier":"s:Sb","text":"Bool","kind":"typeIdentifier"},{"text":", ","kind":"text"},{"text":"dataFieldSizeMetadata","kind":"externalParam"},{"text":": ","kind":"text"},{"kind":"typeIdentifier","text":"DSAPISettingsMetadata","preciseIdentifier":"c:@M@DocuSignAPI@objc(cs)DSAPISettingsMetadata"},{"kind":"text","text":"?, "},{"text":"drawTabsEnabled","kind":"externalParam"},{"kind":"text","text":": "},{"preciseIdentifier":"s:Sb","text":"Bool","kind":"typeIdentifier"},{"kind":"text","text":", "},{"text":"drawTabsMetadata","kind":"externalParam"},{"text":": ","kind":"text"},{"preciseIdentifier":"c:@M@DocuSignAPI@objc(cs)DSAPISettingsMetadata","kind":"typeIdentifier","text":"DSAPISettingsMetadata"},{"text":"?, ","kind":"text"},{"text":"firstLastEmailTabsEnabled","kind":"externalParam"},{"text":": ","kind":"text"},{"text":"Bool","kind":"typeIdentifier","preciseIdentifier":"s:Sb"},{"kind":"text","text":", "},{"text":"firstLastEmailTabsMetadata","kind":"externalParam"},{"kind":"text","text":": "},{"text":"DSAPISettingsMetadata","kind":"typeIdentifier","preciseIdentifier":"c:@M@DocuSignAPI@objc(cs)DSAPISettingsMetadata"},{"text":"?, ","kind":"text"},{"text":"listTabsEnabled","kind":"externalParam"},{"kind":"text","text":": "},{"kind":"typeIdentifier","preciseIdentifier":"s:Sb","text":"Bool"},{"text":", ","kind":"text"},{"kind":"externalParam","text":"listTabsMetadata"},{"text":": ","kind":"text"},{"preciseIdentifier":"c:@M@DocuSignAPI@objc(cs)DSAPISettingsMetadata","text":"DSAPISettingsMetadata","kind":"typeIdentifier"},{"text":"?, ","kind":"text"},{"text":"noteTabsEnabled","kind":"externalParam"},{"text":": ","kind":"text"},{"kind":"typeIdentifier","preciseIdentifier":"s:Sb","text":"Bool"},{"kind":"text","text":", "},{"text":"noteTabsMetadata","kind":"externalParam"},{"text":": ","kind":"text"},{"text":"DSAPISettingsMetadata","kind":"typeIdentifier","preciseIdentifier":"c:@M@DocuSignAPI@objc(cs)DSAPISettingsMetadata"},{"kind":"text","text":"?, "},{"kind":"externalParam","text":"prefillTabsEnabled"},{"kind":"text","text":": "},{"kind":"typeIdentifier","text":"Bool","preciseIdentifier":"s:Sb"},{"kind":"text","text":", "},{"kind":"externalParam","text":"prefillTabsMetadata"},{"text":": ","kind":"text"},{"preciseIdentifier":"c:@M@DocuSignAPI@objc(cs)DSAPISettingsMetadata","text":"DSAPISettingsMetadata","kind":"typeIdentifier"},{"kind":"text","text":"?, "},{"kind":"externalParam","text":"radioTabsEnabled"},{"kind":"text","text":": "},{"preciseIdentifier":"s:Sb","kind":"typeIdentifier","text":"Bool"},{"text":", ","kind":"text"},{"text":"radioTabsMetadata","kind":"externalParam"},{"text":": ","kind":"text"},{"text":"DSAPISettingsMetadata","preciseIdentifier":"c:@M@DocuSignAPI@objc(cs)DSAPISettingsMetadata","kind":"typeIdentifier"},{"kind":"text","text":"?, "},{"kind":"externalParam","text":"savingCustomTabsEnabled"},{"kind":"text","text":": "},{"kind":"typeIdentifier","preciseIdentifier":"s:Sb","text":"Bool"},{"kind":"text","text":", "},{"text":"savingCustomTabsMetadata","kind":"externalParam"},{"text":": ","kind":"text"},{"preciseIdentifier":"c:@M@DocuSignAPI@objc(cs)DSAPISettingsMetadata","text":"DSAPISettingsMetadata","kind":"typeIdentifier"},{"text":"?, ","kind":"text"},{"text":"senderToChangeTabAssignmentsEnabled","kind":"externalParam"},{"text":": ","kind":"text"},{"kind":"typeIdentifier","text":"Bool","preciseIdentifier":"s:Sb"},{"text":", ","kind":"text"},{"text":"senderToChangeTabAssignmentsMetadata","kind":"externalParam"},{"text":": ","kind":"text"},{"preciseIdentifier":"c:@M@DocuSignAPI@objc(cs)DSAPISettingsMetadata","text":"DSAPISettingsMetadata","kind":"typeIdentifier"},{"kind":"text","text":"?, "},{"text":"sharedCustomTabsEnabled","kind":"externalParam"},{"text":": ","kind":"text"},{"text":"Bool","preciseIdentifier":"s:Sb","kind":"typeIdentifier"},{"kind":"text","text":", "},{"kind":"externalParam","text":"sharedCustomTabsMetadata"},{"text":": ","kind":"text"},{"preciseIdentifier":"c:@M@DocuSignAPI@objc(cs)DSAPISettingsMetadata","text":"DSAPISettingsMetadata","kind":"typeIdentifier"},{"text":"?, ","kind":"text"},{"kind":"externalParam","text":"tabDataLabelEnabled"},{"text":": ","kind":"text"},{"kind":"typeIdentifier","text":"Bool","preciseIdentifier":"s:Sb"},{"kind":"text","text":", "},{"text":"tabDataLabelMetadata","kind":"externalParam"},{"text":": ","kind":"text"},{"text":"DSAPISettingsMetadata","preciseIdentifier":"c:@M@DocuSignAPI@objc(cs)DSAPISettingsMetadata","kind":"typeIdentifier"},{"kind":"text","text":"?, "},{"kind":"externalParam","text":"tabLocationEnabled"},{"kind":"text","text":": "},{"text":"Bool","preciseIdentifier":"s:Sb","kind":"typeIdentifier"},{"kind":"text","text":", "},{"text":"tabLocationMetadata","kind":"externalParam"},{"text":": ","kind":"text"},{"text":"DSAPISettingsMetadata","kind":"typeIdentifier","preciseIdentifier":"c:@M@DocuSignAPI@objc(cs)DSAPISettingsMetadata"},{"kind":"text","text":"?, "},{"text":"tabLockingEnabled","kind":"externalParam"},{"kind":"text","text":": "},{"kind":"typeIdentifier","preciseIdentifier":"s:Sb","text":"Bool"},{"text":", ","kind":"text"},{"kind":"externalParam","text":"tabLockingMetadata"},{"text":": ","kind":"text"},{"preciseIdentifier":"c:@M@DocuSignAPI@objc(cs)DSAPISettingsMetadata","text":"DSAPISettingsMetadata","kind":"typeIdentifier"},{"kind":"text","text":"?, "},{"text":"tabScaleEnabled","kind":"externalParam"},{"kind":"text","text":": "},{"preciseIdentifier":"s:Sb","text":"Bool","kind":"typeIdentifier"},{"kind":"text","text":", "},{"kind":"externalParam","text":"tabScaleMetadata"},{"kind":"text","text":": "},{"kind":"typeIdentifier","text":"DSAPISettingsMetadata","preciseIdentifier":"c:@M@DocuSignAPI@objc(cs)DSAPISettingsMetadata"},{"kind":"text","text":"?, "},{"kind":"externalParam","text":"tabTextFormattingEnabled"},{"kind":"text","text":": "},{"text":"Bool","kind":"typeIdentifier","preciseIdentifier":"s:Sb"},{"text":", ","kind":"text"},{"kind":"externalParam","text":"tabTextFormattingMetadata"},{"text":": ","kind":"text"},{"text":"DSAPISettingsMetadata","kind":"typeIdentifier","preciseIdentifier":"c:@M@DocuSignAPI@objc(cs)DSAPISettingsMetadata"},{"text":"?, ","kind":"text"},{"text":"textTabsEnabled","kind":"externalParam"},{"kind":"text","text":": "},{"preciseIdentifier":"s:Sb","text":"Bool","kind":"typeIdentifier"},{"text":", ","kind":"text"},{"text":"textTabsMetadata","kind":"externalParam"},{"text":": ","kind":"text"},{"preciseIdentifier":"c:@M@DocuSignAPI@objc(cs)DSAPISettingsMetadata","kind":"typeIdentifier","text":"DSAPISettingsMetadata"},{"text":"?)","kind":"text"}],"role":"symbol","modules":[{"name":"DocuSignAPI"}]},"references":{"doc://com.DocuSign.DocuSIgnAPI/documentation/DocuSignAPI":{"kind":"symbol","type":"topic","role":"collection","url":"\/documentation\/docusignapi","abstract":[],"title":"DocuSignAPI","identifier":"doc:\/\/com.DocuSign.DocuSIgnAPI\/documentation\/DocuSignAPI"},"doc://com.DocuSign.DocuSIgnAPI/documentation/DocuSignAPI/DSAPISettingsMetadata":{"navigatorTitle":[{"kind":"identifier","text":"DSAPISettingsMetadata"}],"role":"symbol","abstract":[{"type":"text","text":"Metadata that indicates whether a property is editable and describes setting-specific options."}],"title":"DSAPISettingsMetadata","kind":"symbol","url":"\/documentation\/docusignapi\/dsapisettingsmetadata","type":"topic","fragments":[{"text":"class","kind":"keyword"},{"text":" ","kind":"text"},{"text":"DSAPISettingsMetadata","kind":"identifier"}],"identifier":"doc:\/\/com.DocuSign.DocuSIgnAPI\/documentation\/DocuSignAPI\/DSAPISettingsMetadata"},"doc://com.DocuSign.DocuSIgnAPI/documentation/DocuSignAPI/DSAPITabAccountSettings":{"abstract":[],"identifier":"doc:\/\/com.DocuSign.DocuSIgnAPI\/documentation\/DocuSignAPI\/DSAPITabAccountSettings","type":"topic","url":"\/documentation\/docusignapi\/dsapitabaccountsettings","navigatorTitle":[{"text":"DSAPITabAccountSettings","kind":"identifier"}],"title":"DSAPITabAccountSettings","fragments":[{"text":"struct","kind":"keyword"},{"kind":"text","text":" "},{"text":"DSAPITabAccountSettings","kind":"identifier"}],"kind":"symbol","role":"symbol"},"doc://com.DocuSign.DocuSIgnAPI/documentation/DocuSignAPI/DSAPITabAccountSettings/init(allowTabOrder:allowTabOrderMetadata:approveDeclineTabsEnabled:approveDeclineTabsMetadata:calculatedFieldsEnabled:calculatedFieldsMetadata:checkboxTabsEnabled:checkBoxTabsMetadata:currencyTabsEnabled:currencyTabsMetadata:dataFieldRegexEnabled:dataFieldRegexMetadata:dataFieldSizeEnabled:dataFieldSizeMetadata:drawTabsEnabled:drawTabsMetadata:firstLastEmailTabsEnabled:firstLastEmailTabsMetadata:listTabsEnabled:listTabsMetadata:noteTabsEnabled:noteTabsMetadata:prefillTabsEnabled:prefillTabsMetadata:radioTabsEnabled:radioTabsMetadata:savingCustomTabsEnabled:savingCustomTabsMetadata:senderToChangeTabAssignmentsEnabled:senderToChangeTabAssignmentsMetadata:sharedCustomTabsEnabled:sharedCustomTabsMetadata:tabDataLabelEnabled:tabDataLabelMetadata:tabLocationEnabled:tabLocationMetadata:tabLockingEnabled:tabLockingMetadata:tabScaleEnabled:tabScaleMetadata:tabTextFormattingEnabled:tabTextFormattingMetadata:textTabsEnabled:textTabsMetadata:)":{"url":"\/documentation\/docusignapi\/dsapitabaccountsettings\/init(allowtaborder:allowtabordermetadata:approvedeclinetabsenabled:approvedeclinetabsmetadata:calculatedfieldsenabled:calculatedfieldsmetadata:checkboxtabsenabled:checkboxtabsmetadata:currencytabsenabled:currencytabsmetadata:datafieldregexe-98kwl","fragments":[{"kind":"identifier","text":"init"},{"text":"(","kind":"text"},{"kind":"externalParam","text":"allowTabOrder"},{"text":": ","kind":"text"},{"kind":"typeIdentifier","preciseIdentifier":"s:Sb","text":"Bool"},{"text":", ","kind":"text"},{"text":"allowTabOrderMetadata","kind":"externalParam"},{"text":": ","kind":"text"},{"kind":"typeIdentifier","text":"DSAPISettingsMetadata","preciseIdentifier":"c:@M@DocuSignAPI@objc(cs)DSAPISettingsMetadata"},{"text":"?, ","kind":"text"},{"kind":"externalParam","text":"approveDeclineTabsEnabled"},{"text":": ","kind":"text"},{"text":"Bool","kind":"typeIdentifier","preciseIdentifier":"s:Sb"},{"text":", ","kind":"text"},{"kind":"externalParam","text":"approveDeclineTabsMetadata"},{"kind":"text","text":": "},{"kind":"typeIdentifier","preciseIdentifier":"c:@M@DocuSignAPI@objc(cs)DSAPISettingsMetadata","text":"DSAPISettingsMetadata"},{"kind":"text","text":"?, "},{"text":"calculatedFieldsEnabled","kind":"externalParam"},{"kind":"text","text":": "},{"preciseIdentifier":"s:Sb","text":"Bool","kind":"typeIdentifier"},{"kind":"text","text":", "},{"kind":"externalParam","text":"calculatedFieldsMetadata"},{"text":": ","kind":"text"},{"text":"DSAPISettingsMetadata","preciseIdentifier":"c:@M@DocuSignAPI@objc(cs)DSAPISettingsMetadata","kind":"typeIdentifier"},{"text":"?, ","kind":"text"},{"text":"checkboxTabsEnabled","kind":"externalParam"},{"kind":"text","text":": "},{"text":"Bool","preciseIdentifier":"s:Sb","kind":"typeIdentifier"},{"text":", ","kind":"text"},{"text":"checkBoxTabsMetadata","kind":"externalParam"},{"text":": ","kind":"text"},{"preciseIdentifier":"c:@M@DocuSignAPI@objc(cs)DSAPISettingsMetadata","text":"DSAPISettingsMetadata","kind":"typeIdentifier"},{"text":"?, ","kind":"text"},{"text":"currencyTabsEnabled","kind":"externalParam"},{"text":": ","kind":"text"},{"preciseIdentifier":"s:Sb","text":"Bool","kind":"typeIdentifier"},{"kind":"text","text":", "},{"text":"currencyTabsMetadata","kind":"externalParam"},{"kind":"text","text":": "},{"kind":"typeIdentifier","text":"DSAPISettingsMetadata","preciseIdentifier":"c:@M@DocuSignAPI@objc(cs)DSAPISettingsMetadata"},{"text":"?, ","kind":"text"},{"text":"dataFieldRegexEnabled","kind":"externalParam"},{"text":": ","kind":"text"},{"preciseIdentifier":"s:Sb","text":"Bool","kind":"typeIdentifier"},{"text":", ","kind":"text"},{"text":"dataFieldRegexMetadata","kind":"externalParam"},{"text":": ","kind":"text"},{"preciseIdentifier":"c:@M@DocuSignAPI@objc(cs)DSAPISettingsMetadata","kind":"typeIdentifier","text":"DSAPISettingsMetadata"},{"kind":"text","text":"?, "},{"text":"dataFieldSizeEnabled","kind":"externalParam"},{"text":": ","kind":"text"},{"text":"Bool","kind":"typeIdentifier","preciseIdentifier":"s:Sb"},{"kind":"text","text":", "},{"kind":"externalParam","text":"dataFieldSizeMetadata"},{"kind":"text","text":": "},{"text":"DSAPISettingsMetadata","kind":"typeIdentifier","preciseIdentifier":"c:@M@DocuSignAPI@objc(cs)DSAPISettingsMetadata"},{"text":"?, ","kind":"text"},{"text":"drawTabsEnabled","kind":"externalParam"},{"text":": ","kind":"text"},{"preciseIdentifier":"s:Sb","text":"Bool","kind":"typeIdentifier"},{"text":", ","kind":"text"},{"text":"drawTabsMetadata","kind":"externalParam"},{"text":": ","kind":"text"},{"text":"DSAPISettingsMetadata","kind":"typeIdentifier","preciseIdentifier":"c:@M@DocuSignAPI@objc(cs)DSAPISettingsMetadata"},{"kind":"text","text":"?, "},{"kind":"externalParam","text":"firstLastEmailTabsEnabled"},{"text":": ","kind":"text"},{"kind":"typeIdentifier","preciseIdentifier":"s:Sb","text":"Bool"},{"text":", ","kind":"text"},{"kind":"externalParam","text":"firstLastEmailTabsMetadata"},{"text":": ","kind":"text"},{"text":"DSAPISettingsMetadata","kind":"typeIdentifier","preciseIdentifier":"c:@M@DocuSignAPI@objc(cs)DSAPISettingsMetadata"},{"kind":"text","text":"?, "},{"kind":"externalParam","text":"listTabsEnabled"},{"text":": ","kind":"text"},{"preciseIdentifier":"s:Sb","text":"Bool","kind":"typeIdentifier"},{"kind":"text","text":", "},{"text":"listTabsMetadata","kind":"externalParam"},{"text":": ","kind":"text"},{"text":"DSAPISettingsMetadata","preciseIdentifier":"c:@M@DocuSignAPI@objc(cs)DSAPISettingsMetadata","kind":"typeIdentifier"},{"kind":"text","text":"?, "},{"text":"noteTabsEnabled","kind":"externalParam"},{"kind":"text","text":": "},{"preciseIdentifier":"s:Sb","kind":"typeIdentifier","text":"Bool"},{"kind":"text","text":", "},{"text":"noteTabsMetadata","kind":"externalParam"},{"kind":"text","text":": "},{"kind":"typeIdentifier","preciseIdentifier":"c:@M@DocuSignAPI@objc(cs)DSAPISettingsMetadata","text":"DSAPISettingsMetadata"},{"text":"?, ","kind":"text"},{"text":"prefillTabsEnabled","kind":"externalParam"},{"text":": ","kind":"text"},{"preciseIdentifier":"s:Sb","text":"Bool","kind":"typeIdentifier"},{"kind":"text","text":", "},{"kind":"externalParam","text":"prefillTabsMetadata"},{"kind":"text","text":": "},{"preciseIdentifier":"c:@M@DocuSignAPI@objc(cs)DSAPISettingsMetadata","kind":"typeIdentifier","text":"DSAPISettingsMetadata"},{"text":"?, ","kind":"text"},{"text":"radioTabsEnabled","kind":"externalParam"},{"kind":"text","text":": "},{"kind":"typeIdentifier","text":"Bool","preciseIdentifier":"s:Sb"},{"kind":"text","text":", "},{"kind":"externalParam","text":"radioTabsMetadata"},{"kind":"text","text":": "},{"kind":"typeIdentifier","preciseIdentifier":"c:@M@DocuSignAPI@objc(cs)DSAPISettingsMetadata","text":"DSAPISettingsMetadata"},{"text":"?, ","kind":"text"},{"text":"savingCustomTabsEnabled","kind":"externalParam"},{"text":": ","kind":"text"},{"preciseIdentifier":"s:Sb","kind":"typeIdentifier","text":"Bool"},{"kind":"text","text":", "},{"text":"savingCustomTabsMetadata","kind":"externalParam"},{"text":": ","kind":"text"},{"text":"DSAPISettingsMetadata","kind":"typeIdentifier","preciseIdentifier":"c:@M@DocuSignAPI@objc(cs)DSAPISettingsMetadata"},{"text":"?, ","kind":"text"},{"kind":"externalParam","text":"senderToChangeTabAssignmentsEnabled"},{"text":": ","kind":"text"},{"preciseIdentifier":"s:Sb","kind":"typeIdentifier","text":"Bool"},{"text":", ","kind":"text"},{"text":"senderToChangeTabAssignmentsMetadata","kind":"externalParam"},{"kind":"text","text":": "},{"text":"DSAPISettingsMetadata","preciseIdentifier":"c:@M@DocuSignAPI@objc(cs)DSAPISettingsMetadata","kind":"typeIdentifier"},{"text":"?, ","kind":"text"},{"kind":"externalParam","text":"sharedCustomTabsEnabled"},{"text":": ","kind":"text"},{"kind":"typeIdentifier","preciseIdentifier":"s:Sb","text":"Bool"},{"text":", ","kind":"text"},{"kind":"externalParam","text":"sharedCustomTabsMetadata"},{"text":": ","kind":"text"},{"text":"DSAPISettingsMetadata","kind":"typeIdentifier","preciseIdentifier":"c:@M@DocuSignAPI@objc(cs)DSAPISettingsMetadata"},{"text":"?, ","kind":"text"},{"text":"tabDataLabelEnabled","kind":"externalParam"},{"kind":"text","text":": "},{"kind":"typeIdentifier","preciseIdentifier":"s:Sb","text":"Bool"},{"kind":"text","text":", "},{"kind":"externalParam","text":"tabDataLabelMetadata"},{"text":": ","kind":"text"},{"text":"DSAPISettingsMetadata","kind":"typeIdentifier","preciseIdentifier":"c:@M@DocuSignAPI@objc(cs)DSAPISettingsMetadata"},{"kind":"text","text":"?, "},{"text":"tabLocationEnabled","kind":"externalParam"},{"kind":"text","text":": "},{"text":"Bool","preciseIdentifier":"s:Sb","kind":"typeIdentifier"},{"text":", ","kind":"text"},{"text":"tabLocationMetadata","kind":"externalParam"},{"kind":"text","text":": "},{"preciseIdentifier":"c:@M@DocuSignAPI@objc(cs)DSAPISettingsMetadata","text":"DSAPISettingsMetadata","kind":"typeIdentifier"},{"kind":"text","text":"?, "},{"kind":"externalParam","text":"tabLockingEnabled"},{"text":": ","kind":"text"},{"kind":"typeIdentifier","text":"Bool","preciseIdentifier":"s:Sb"},{"kind":"text","text":", "},{"text":"tabLockingMetadata","kind":"externalParam"},{"kind":"text","text":": "},{"text":"DSAPISettingsMetadata","kind":"typeIdentifier","preciseIdentifier":"c:@M@DocuSignAPI@objc(cs)DSAPISettingsMetadata"},{"kind":"text","text":"?, "},{"kind":"externalParam","text":"tabScaleEnabled"},{"text":": ","kind":"text"},{"preciseIdentifier":"s:Sb","text":"Bool","kind":"typeIdentifier"},{"text":", ","kind":"text"},{"kind":"externalParam","text":"tabScaleMetadata"},{"kind":"text","text":": "},{"text":"DSAPISettingsMetadata","kind":"typeIdentifier","preciseIdentifier":"c:@M@DocuSignAPI@objc(cs)DSAPISettingsMetadata"},{"kind":"text","text":"?, "},{"kind":"externalParam","text":"tabTextFormattingEnabled"},{"text":": ","kind":"text"},{"text":"Bool","kind":"typeIdentifier","preciseIdentifier":"s:Sb"},{"kind":"text","text":", "},{"text":"tabTextFormattingMetadata","kind":"externalParam"},{"kind":"text","text":": "},{"text":"DSAPISettingsMetadata","kind":"typeIdentifier","preciseIdentifier":"c:@M@DocuSignAPI@objc(cs)DSAPISettingsMetadata"},{"text":"?, ","kind":"text"},{"text":"textTabsEnabled","kind":"externalParam"},{"kind":"text","text":": "},{"text":"Bool","preciseIdentifier":"s:Sb","kind":"typeIdentifier"},{"kind":"text","text":", "},{"text":"textTabsMetadata","kind":"externalParam"},{"text":": ","kind":"text"},{"kind":"typeIdentifier","text":"DSAPISettingsMetadata","preciseIdentifier":"c:@M@DocuSignAPI@objc(cs)DSAPISettingsMetadata"},{"kind":"text","text":"?)"}],"title":"init(allowTabOrder:allowTabOrderMetadata:approveDeclineTabsEnabled:approveDeclineTabsMetadata:calculatedFieldsEnabled:calculatedFieldsMetadata:checkboxTabsEnabled:checkBoxTabsMetadata:currencyTabsEnabled:currencyTabsMetadata:dataFieldRegexEnabled:dataFieldRegexMetadata:dataFieldSizeEnabled:dataFieldSizeMetadata:drawTabsEnabled:drawTabsMetadata:firstLastEmailTabsEnabled:firstLastEmailTabsMetadata:listTabsEnabled:listTabsMetadata:noteTabsEnabled:noteTabsMetadata:prefillTabsEnabled:prefillTabsMetadata:radioTabsEnabled:radioTabsMetadata:savingCustomTabsEnabled:savingCustomTabsMetadata:senderToChangeTabAssignmentsEnabled:senderToChangeTabAssignmentsMetadata:sharedCustomTabsEnabled:sharedCustomTabsMetadata:tabDataLabelEnabled:tabDataLabelMetadata:tabLocationEnabled:tabLocationMetadata:tabLockingEnabled:tabLockingMetadata:tabScaleEnabled:tabScaleMetadata:tabTextFormattingEnabled:tabTextFormattingMetadata:textTabsEnabled:textTabsMetadata:)","abstract":[],"type":"topic","kind":"symbol","identifier":"doc:\/\/com.DocuSign.DocuSIgnAPI\/documentation\/DocuSignAPI\/DSAPITabAccountSettings\/init(allowTabOrder:allowTabOrderMetadata:approveDeclineTabsEnabled:approveDeclineTabsMetadata:calculatedFieldsEnabled:calculatedFieldsMetadata:checkboxTabsEnabled:checkBoxTabsMetadata:currencyTabsEnabled:currencyTabsMetadata:dataFieldRegexEnabled:dataFieldRegexMetadata:dataFieldSizeEnabled:dataFieldSizeMetadata:drawTabsEnabled:drawTabsMetadata:firstLastEmailTabsEnabled:firstLastEmailTabsMetadata:listTabsEnabled:listTabsMetadata:noteTabsEnabled:noteTabsMetadata:prefillTabsEnabled:prefillTabsMetadata:radioTabsEnabled:radioTabsMetadata:savingCustomTabsEnabled:savingCustomTabsMetadata:senderToChangeTabAssignmentsEnabled:senderToChangeTabAssignmentsMetadata:sharedCustomTabsEnabled:sharedCustomTabsMetadata:tabDataLabelEnabled:tabDataLabelMetadata:tabLocationEnabled:tabLocationMetadata:tabLockingEnabled:tabLockingMetadata:tabScaleEnabled:tabScaleMetadata:tabTextFormattingEnabled:tabTextFormattingMetadata:textTabsEnabled:textTabsMetadata:)","role":"symbol"}},"variantOverrides":[{"traits":[{"interfaceLanguage":"occ"}],"patch":[{"path":"\/references\/doc:~1~1com.DocuSign.DocuSIgnAPI~1documentation~1DocuSignAPI~1DSAPISettingsMetadata\/title","op":"replace","value":"DSAPISettingsMetadata"},{"op":"replace","path":"\/references\/doc:~1~1com.DocuSign.DocuSIgnAPI~1documentation~1DocuSignAPI~1DSAPISettingsMetadata\/fragments","value":[{"text":"DSAPISettingsMetadata","kind":"identifier"}]}]}]}